<TextObjectProperties>
  <Layout>
    <Frame>
      <BorderWidth>0</BorderWidth>
      <BorderEffect>FLAT</BorderEffect>
      <Color>
        <Mode>COLORAREA_SOLID</Mode>
        <Luminosity>85</Luminosity>
        <FillDirection>COLORAREA_HORZ</FillDirection>
        <FillPattern>COLORAREA_PATTERN1</FillPattern>
        <PrimaryCol>
          <Col>
            <Red>4</Red>
            <Green>108</Green>
            <Blue>193</Blue>
            <Alpha>255</Alpha>
          </Col>
          <IsCalculated>false</IsCalculated>
          <ColorExpr></ColorExpr>
        </PrimaryCol>
        <SecondaryCol></SecondaryCol>
        <Alpha>255</Alpha>
      </Color>
      <Font></Font>
      <CaptionFont>
        <FontName>Tahoma</FontName>
        <PointSize1000>10000</PointSize1000>
        <Underline>false</Underline>
        <Bold>true</Bold>
        <Italic>false</Italic>
        <DropShadow>false</DropShadow>
      </CaptionFont>
      <Name></Name>
      <Bmp enctype="base64"></Bmp>
      <BmpMode>0</BmpMode>
      <Detached>false</Detached>
      <AllowMinimize>false</AllowMinimize>
      <AutoMinimize>false</AutoMinimize>
      <AllowMaximize>false</AllowMaximize>
      <AllowInfo>false</AllowInfo>
      <PrintIcon>false</PrintIcon>
      <CopyIcon>false</CopyIcon>
      <XLIcon>false</XLIcon>
      <SearchIcon>false</SearchIcon>
      <SelectPossibleIcon>false</SelectPossibleIcon>
      <SelectExcludedIcon>false</SelectExcludedIcon>
      <SelectAllIcon>false</SelectAllIcon>
      <ClearIcon>false</ClearIcon>
      <ClearOtherIcon>false</ClearOtherIcon>
      <LockIcon>false</LockIcon>
      <HelpText></HelpText>
      <ObjectId></ObjectId>
      <ShrinkFrameToData>true</ShrinkFrameToData>
      <ShowCaption>false</ShowCaption>
      <MultiLine>0</MultiLine>
      <ActiveBgColor>
        <Mode>COLORAREA_SOLID</Mode>
        <Luminosity>85</Luminosity>
        <FillDirection>COLORAREA_HORZ</FillDirection>
        <FillPattern>COLORAREA_PATTERN1</FillPattern>
        <PrimaryCol>
          <Col>
            <Red>210</Red>
            <Green>210</Green>
            <Blue>210</Blue>
            <Alpha>255</Alpha>
          </Col>
          <IsCalculated>false</IsCalculated>
          <ColorExpr></ColorExpr>
        </PrimaryCol>
        <SecondaryCol>
          <Col>
            <Red>153</Red>
            <Green>153</Green>
            <Blue>153</Blue>
            <Alpha>255</Alpha>
          </Col>
          <IsCalculated>false</IsCalculated>
          <ColorExpr></ColorExpr>
        </SecondaryCol>
        <Alpha>255</Alpha>
      </ActiveBgColor>
      <BgColor>
        <Mode>COLORAREA_SOLID</Mode>
        <Luminosity>85</Luminosity>
        <FillDirection>COLORAREA_HORZ</FillDirection>
        <FillPattern>COLORAREA_PATTERN1</FillPattern>
        <PrimaryCol>
          <Col>
            <Red>232</Red>
            <Green>232</Green>
            <Blue>232</Blue>
            <Alpha>255</Alpha>
          </Col>
          <IsCalculated>false</IsCalculated>
          <ColorExpr></ColorExpr>
        </PrimaryCol>
        <SecondaryCol>
          <Col>
            <Red>200</Red>
            <Green>200</Green>
            <Blue>200</Blue>
            <Alpha>255</Alpha>
          </Col>
          <IsCalculated>false</IsCalculated>
          <ColorExpr></ColorExpr>
        </SecondaryCol>
        <Alpha>255</Alpha>
      </BgColor>
      <ActiveFgColor>
        <Mode>COLORAREA_SOLID</Mode>
        <Luminosity>85</Luminosity>
        <FillDirection>COLORAREA_HORZ</FillDirection>
        <FillPattern>COLORAREA_PATTERN1</FillPattern>
        <PrimaryCol>
          <Col>
            <Red>54</Red>
            <Green>54</Green>
            <Blue>54</Blue>
            <Alpha>255</Alpha>
          </Col>
          <IsCalculated>false</IsCalculated>
          <ColorExpr></ColorExpr>
        </PrimaryCol>
        <SecondaryCol></SecondaryCol>
        <Alpha>255</Alpha>
      </ActiveFgColor>
      <FgColor>
        <Mode>COLORAREA_SOLID</Mode>
        <Luminosity>85</Luminosity>
        <FillDirection>COLORAREA_HORZ</FillDirection>
        <FillPattern>COLORAREA_PATTERN1</FillPattern>
        <PrimaryCol>
          <Col>
            <Red>54</Red>
            <Green>54</Green>
            <Blue>54</Blue>
            <Alpha>255</Alpha>
          </Col>
          <IsCalculated>false</IsCalculated>
          <ColorExpr></ColorExpr>
        </PrimaryCol>
        <SecondaryCol></SecondaryCol>
        <Alpha>255</Alpha>
      </FgColor>
      <FixCorner>true</FixCorner>
      <FixCornerSize>21</FixCornerSize>
      <RelCornerSize>4059000000000000</RelCornerSize>
      <Power>4000000000000000</Power>
      <RoundedShape>true</RoundedShape>
      <EnableTopLeftRounded>true</EnableTopLeftRounded>
      <EnableTopRightRounded>true</EnableTopRightRounded>
      <EnableBottomLeftRounded>true</EnableBottomLeftRounded>
      <EnableBottomRightRounded>true</EnableBottomRightRounded>
      <Light>3FEE666666666666</Light>
      <Dark>3FC3333333333333</Dark>
      <Rainbow>false</Rainbow>
      <TextAdjustHorizontal>0</TextAdjustHorizontal>
      <TextAdjustVertical>4</TextAdjustVertical>
      <Show></Show>
      <AllowMoveSize>true</AllowMoveSize>
      <AllowCopyClone>true</AllowCopyClone>
      <dummy></dummy>
      <CustomObjectGuid enctype="base64"></CustomObjectGuid>
      <CustomObjectProperties enctype="base64"></CustomObjectProperties>
      <ScrollBkgColor>
        <Col>
          <Red>255</Red>
          <Green>255</Green>
          <Blue>255</Blue>
          <Alpha>255</Alpha>
        </Col>
        <IsCalculated>false</IsCalculated>
        <ColorExpr></ColorExpr>
      </ScrollBkgColor>
      <ScrollButtonColor>
        <Col>
          <Red>192</Red>
          <Green>192</Green>
          <Blue>192</Blue>
          <Alpha>255</Alpha>
        </Col>
        <IsCalculated>false</IsCalculated>
        <ColorExpr></ColorExpr>
      </ScrollButtonColor>
      <ScrollStyle>SCROLL_SIX</ScrollStyle>
      <ScrollWidth>38</ScrollWidth>
      <AllowModify>true</AllowModify>
      <CopyImageIcon>false</CopyImageIcon>
      <PreserveScrollPosition>false</PreserveScrollPosition>
      <ShadowIntensity>SHADOW_NONE</ShadowIntensity>
      <OnActivateActionItems></OnActivateActionItems>
      <OnDeactivateActionItems></OnDeactivateActionItems>
      <Extension></Extension>
      <Background></Background>
      <MenuIcon>false</MenuIcon>
      <ExtendedProperties></ExtendedProperties>
      <ExtendedValues></ExtendedValues>
      <StateName></StateName>
    </Frame>
    <LegacyHelpModeThatHasNoEffectWhatSoEver>false</LegacyHelpModeThatHasNoEffectWhatSoEver>
    <TextAdjustHorizontal>1</TextAdjustHorizontal>
    <TextAdjustVertical>4</TextAdjustVertical>
    <TopMargin>10</TopMargin>
    <BottomMargin>10</BottomMargin>
    <LeftMargin>10</LeftMargin>
    <RightMargin>10</RightMargin>
    <TextColor>
      <Mode>COLORAREA_SOLID</Mode>
      <Luminosity>85</Luminosity>
      <FillDirection>COLORAREA_HORZ</FillDirection>
      <FillPattern>COLORAREA_PATTERN1</FillPattern>
      <PrimaryCol>
        <Col>
          <Red>54</Red>
          <Green>54</Green>
          <Blue>54</Blue>
          <Alpha>255</Alpha>
        </Col>
        <IsCalculated>false</IsCalculated>
        <ColorExpr></ColorExpr>
      </PrimaryCol>
      <SecondaryCol></SecondaryCol>
      <Alpha>255</Alpha>
    </TextColor>
    <BkgColor>
      <Mode>COLORAREA_SOLID</Mode>
      <Luminosity>85</Luminosity>
      <FillDirection>COLORAREA_HORZ</FillDirection>
      <FillPattern>COLORAREA_PATTERN1</FillPattern>
      <PrimaryCol>
        <Col>
          <Red>214</Red>
          <Green>231</Green>
          <Blue>248</Blue>
          <Alpha>255</Alpha>
        </Col>
        <IsCalculated>false</IsCalculated>
        <ColorExpr></ColorExpr>
      </PrimaryCol>
      <SecondaryCol></SecondaryCol>
      <Alpha>255</Alpha>
    </BkgColor>
    <BkgImageSettings>
      <ImageStyle>
        <StretchMode>IMAGE_KEEPASPECT</StretchMode>
        <ImgFallBack>0</ImgFallBack>
      </ImageStyle>
      <HorizontalAdjust>0</HorizontalAdjust>
      <VerticalAdjust>4</VerticalAdjust>
    </BkgImageSettings>
    <BkgMode>BKG_IMAGE</BkgMode>
    <Bmp enctype="base64">
        iVBORw0KGgoAAAANSUhEUgAAAgkAAADyCAYAAADHqFYLAAAACXBIWXMAAA7DAAAOwwHHb6hkAAAg
        AElEQVR4nOydB5xU1b3H/3fa9uLSlmVpIk1BpQsKiiV2eUYfsYAiRIkSfcYkSiwRO6DYjeUlERFb
        iA1LjEYiLkh4SJOyVNkFFpAtbJltU+5953cLc/feM7Mzu7OUnfPV87mz95S5w8y953/+7ThJIEhs
        urPSS39dG4fxurHSm5VkVqriMJ5AIBAIBIIW8jArB5opHTn9prKymxXFVNazMqEF1+Bi5Q+s7LWM
        h/d+iBVPC8YUCAQCgUDQSr6iphMzr3S29HnQVPcvVl5iZZnp3M0xvL+DlU/1fn5WFrPyHCufsxLU
        z/+ThKAgEAgEAsERp5S0iXgEK13CFIep/YmkTeboc5NlrD/o52uIr33gcbPep5yVwZa6kaSZHFB/
        e5TjCQQCgUAgiAN5pE3Asdj+f6X3WcupgzCxR6+/OsrxVurt/ydMvSF4rIjhGgUCgeCYwNF8E4Hg
        mGWQfvw+hj4u/VjBqZNJ8yMA2VGOh3voECtLw9QbwsiJUY4nEAgExwyu5psIBMcsw/UjJmL8lk8n
        LboAAgBW+D5On436cShpvgoHTXX5FBI81kR5DSOaqTdMEHujHE8gEAgEAkEceJ80VT6O1sgC+Ajc
        EabfR3qb1aycR5pgcTErm/Tz8+N0fQiDLNbHfDhOYwoEAoHgCIBVJMLTviFtJQoP9dtIe7CHA6rl
        X7DyN73Pl6w8wUrXVl7HH0nzsl+vj3kXK6mtGDNR2EkhoQATPKIUEFmwwXR+HqcfIg3uJ34kxEyK
        nxnuFX3Mn1jJidOYAoFAIGhjxpC20jQmhmrT6y0USq5jJp20idxoV09a8h28bmTlv1twHZdSyPsd
        pdJyHdF62CciEKKMf6t7qenEjtd/NNWfZel7N2kRDKhbRZrQt55CGojr43B9T1Lot3F+HMYTCAQC
        wREgk5X9pD3A3yUtRA70JG0VbyTVsfI2hcLjIBDABo7J6CrSJnrExJ8dw3WcRJqggTFfIE0IAbCV
        b9HPfxzDeIkINAKRHAKXk/bv+Jbp3HT9HJwNrcIDhDYIfvguL2vhNeE38RqFBIRftHAcgUAgEBwF
        fkMh9bQ1wQ0ECGNlb55ATqXQqvRczpiXmcaMlkV6n79y6k42vV9eDGMKmvJb0v4NN5jOGQLiNWH6
        3E6xf5cGEPQMQRPC5KUtGEMgEAgERxGopgtJUznzMFafU03nZlLzse6Gg9rIKK4B9mkk9MGq1ZoN
        0ABZAR8hvulDEB0QBPCd7NL/zqeQ8BXO5yPX1CY9TBseGHuj3g+CyPDIzQUCgUBwvAFVcQlpD/qL
        TOf/op97KUJfIz1wNJn1/ktv+4+WXaaAMYqVOaT5HoTj96T9Oxfof/ejkAAQzkE13dQmnABnpQeF
        hMQfSBMYBAKB4LhHJFMKgUkDkw7U+z+S5qRoIEfR3zBdnBxF2yH6cbV+hC/Di6Tl+/8zK5dHMUai
        A18SaIMeoPCJjybqxy/1YxErdfrrc8L0OUM/wom0LIrrgInqa9IEBez/AKdYkRNBIBAI2glwLINT
        4j4K2a/7WdoYtu1VYcaAgGBES7wVpo2Zt/S2v2ZlAfFD8SAwxKLuTjRgLkBoIf6tFpJd4DVCHOGg
        aI4SMcISt5JdU4B2hXr985a6saxMJrufgTHedoo+S6NA0N7BMxF5ShAqjuRmELi/JW2/lEiL0wtI
        2yQNz2OYY3E/Iow5XpFe0PQiq+qjcRpPkAB8Rk0nZ6w6x1raQGgwdvSbxhnDHG73ThTvaSQB2qqP
        CzMGVrBwkESOBCM8b2FsHyXhuJJC3wsyLMLf5E5WllAousA6qWMiN6JHsDkUQhVnkJbvwhA6YDKw
        CmjvkH3PB5gVjM2imis/tfKzCgTHC9DKwsRn7IyKiX47he6FvxNfUPidqQ2EBESZGRFg8PNpbWrz
        AabxnmvlWIIEAuYBqK7xA3qGQpPLVZZ2L+p1mJQQkTBBb2OERq6i6DUJ5u2NeQ6U40z1p8b0aRIP
        ZEw0MiWaCx4w4UJSIShAg2Od4PE3whczOX14QsJEzvsKIUGQ6DxGfAfe8RSKHrvV0gfp0A2BH8KC
        IUTAkXgphRYCLQWaDXOSNSEkRIl0tC/gGGQ2K/eQZr/uy0pAP48f2bNk/3GjHjv9JZGmwnqF08bK
        e6RNMNg3oJvpPczgxhinjz07xs/QrqgvXNtLKt//WrAiNM+yH24DaX4DKgWbtmYXFpdkOBwOZWD3
        vJozT+lXpZAUkDQzEJc9ZeXJS9Zu6rxz38FAbk5W9RWjh5Tkd8xp4LXdtb+0obzaS8lJnuDgXvle
        nNtfUeXZW1qeYrRplAO1vkZ/La+/y+WQzz5lYJUiKb6g4jxEaWmU5uywTRo/nvt+AsFxDDKhYtUP
        ras1xBvPVjzPsDfKMNP5x0l71kELeJ6lj+EYDPqQ5jMWK/A3w4IMz1yYGWFODLdzq8CE2ODJztOk
        /ZB7kfZD36afx2ZBSNuMlSYcC42kTJjwERHxut5uexTvUa0fNxNfQABQeUNI6BvT1bdDHAd2pfu2
        rLugbvm7pAT93Dan6UXlEPsH/qH5cbNIs1eo4h+m/a++O/zFWOmgF1ClB8LCKcLqvBKJSiNbg8NB
        SX1HU23PQdASbYjURyA4DjFyu2zk1BmaOGsEUDf9uJnTZzdpCwJoACEwxCokILcNtBMwgcBZ/M4Y
        +yc0iSgk4MEMafTfZFqJmjDvCghV1zZL/Tq9WBmqH6OYng7vMBhpfwZD3VYXoU3ioMjkrygmJdB4
        tK+k1UgOJ3l6nNZ8Q4Hg+ATPTDxnsUPq/1nqDO2BdaLfoh95eWYgGBhOwbEKCOj3BmnLgOtIS6Yn
        iIFEDIGE0+AHpOUq4GF2jikynZtPmhaBB1Is46bAhP5dFNewXD9ia2Oe/RsYWxavDVMvEAgExyJz
        9SPMrxeYzsOPC1FHCCl/zNIHmlhEQEBIgOnBCCnvTpq2FsAvaHeM1/In0rQWiLQQocktIBGFBCOB
        EcIarWmZgbGlL1b7xg8SUig2/YGNjadhNm4KSKzRrPyhbdiov/8DnHokCkJaaJg4PopivIRFcjjU
        lTm3SNH9vNW27iR7cblb118tHnYdwvVHkFDAeXsSaZEEiBar0AueZYgogj/Wp5Y+CEuEeRUaXvgm
        IMILEQ54BmMxBX+wKTFeB57Z17LyIWnPZkELSERzA6Rb/HCwUscPGM4sxs6PCKFD3gTD/8AAJohF
        ej9oIX5F2iQPCXUWaabtA/prM3CQMbztLqRQUh9wC2nbVMNWhpCh5/X3uUR/jRkOW1lXtPyjtm8g
        ILh6DyFnR5gz7ROx7D1E/q3/ISXgizhO8oiLKfW8Sbbz/p3rqObDZ0nxhfctlJwuSvvZTZQ0xOpr
        pRE4sItq/jaXFO+hyB9GIGg/wIyKqIYM/W9oDgyJHa5A0Lp+SPYkdTDZGr4JAb0P2mAxBY0CzL/R
        ahJgooAWAc/lW2L+BILDJKKQgIkYjiyfkBYiZw2rgcrrGs55/NB6k5bPoMBSh3wHV1JTf4bmgPvb
        1aSF4v1aL2YgKCR0VENzKLJMcsU+cvcfRVKK3WrjDAZIaailwI9rSFGUsOO4ug+glLPtmzU60rLI
        u/glUogvJEAsSRo0ljKnPk6OTHuuF7x35Qu3klJXFf2HEgiObzCx/5M0Tej3pCVPMhwYkY0U0Q7I
        KwOH7OtM/bDwepk0rS0kdpgYICggPB2RCTeS5uMwmjQNQ3PXgNB0PBRwY0eTOVUQhnYtJPi3bhob
        2L+zFwWDh89JklxBsuQrKa2YcecLr47fXLR3UE19faeMlJTSk7p13TJ3xk1L+vbMq3UGXbb8BGWV
        lbdNenTe+dv2lIzyNjZ0UhR5d8fs7OXP3T798/HDh8Cjrou5/QfLliTdMOu53+t/Wh0gAQQV3CwQ
        SmCLQwIfhA9BXcdzjhRYkCsPkL/wO/KcyuQ+l8V6xFb57n6jVEEieGh/3N8bGozMGx/hCggkB6nu
        q/lU9+0iVZgRCBIE7IgLAQEa0AupqSYU/lpYoGFRBa0sVvpIZQ7Ng+Gj8EsK+SAAaGKnkPZsxX46
        8Gkwa3l5QDt7Jiv/y8oXLf4kApV2bSyt/+aTdxq/W3yNXHPMC5LlUvhQSIMq8qQ0uPsM+yb9ht8m
        VHxv478/GOQrXLOh6tMnudENUPl7TjufXL1P5/aXf9pFDSs/IsXPj4zIuPp3lHXzk/b3/f4LKn90
        Isn1Nfb3dDgpa9psSr/qLvxhq/dt+JbKH5vIhBN7DiX0TR0yge7zjvxkXaXEi7BpgiIxFDUPR+R2
        TByRNFNZu0Ahckvs2z3a13HcoCgBxaGqvXYrimNLg9RYsH7B/SVH+CqgDYBWAHvQ3BymDRZB0CJA
        MMCkjwUSNLeIQD6B+Hvl/Iw0DUURaRrdSOBGx4oBDuJWH7H+pJkiYLaAsIL7byIJwtKuNQnUWEv+
        oh+ooag1ibqOCB2ab0JdXFldydWxR1FbX8zxhhIMqL4HjsxO5OjQzVbv6NSD3CcNJ/+WFew52vpV
        PRwRk0dfQWkXTuMKCHJZCVXNv58rIJip9EuXhzeCmFAUiqodUdTtjhei/+QCdcmnGC9lSlHcdMbk
        uatJkt9Orm947ZtFs7xH4CqMUMVIKzPDLNtTPxqqOPQJd4Pus7SNhKFSPDNCmx56icVEnJAkYnSD
        oB0i11aSb9O3bB3N8R9gK3cICRAW4oEztzdlTX6IpIwT7JX+Rqp+93HybY4mElYgaGuUYaRI8xqS
        U4rPuHH23eecM6utF4aG5oKv1tMYoB936EdDAIAjeE6YPsbOuQeiuIbTIpQFepu39b/HRzFeQiOE
        BEG7QS7bQ/6tK4iCHMuNJ4U8g84mR3LrNtZ0pKRT5nUPkKvXKZwLkKm+YBHVff0mKXLQXi8QHD1y
        SJbmNHRPWX7WDfNiSRQaK+/qR5gHxnHqz9LroDF4Xz8H/ysIDNAAzOL0wU07U3/9tqUOWlj4K2SZ
        zv0QoRgajjL9b16GR4GJ9m1uCIMjJYOcHfO5qmKoo+WyvVw7tBnYlZPHTCApyZI0kU1Qvk3LKVC6
        J3J/TzKljLpUnbzsKBQo3ky+HSKPUizgu/P/uIYc2bnk7I7FSlOXG5x39xtJvo1LWzyJp4ybSKnj
        r+X+dvw711LVG38kuS7yb0cgOIqM9CuBlaNumH35ygUzl7XB+IhoeJWV6aT5EDxF2k67kNzheIiU
        97h5kPfAnLbZaI+tnKHyg9MhHqKQxhGajo344Pw9z/J+/yJNa4Edcye3wedJeBJSSIAN29nrNCYo
        dOdUsgl6byH51n0VOb7e5abs6U+TMyevyWnFV0cVT06JKCRAwEi7aBplTX2CJHey9QIoWL6Pyh+5
        OoZPJDBQAn7yFS6jpMwO5Mjq3LRSksjFvndFDpDCJnLFV0/B/Tv4AzGcnXpQ2sW/PJwnQUpOpfTL
        biNy230I5cqDVP3mg2pehGjJzj2ROvis379A0DLUxGLsv4C/nnz1Xmr0VrLXdvObBL8BRfrH6Emz
        L1yxcGZb2MUQzg1JGXsk3K8XAzxUEdp9n6UPNna6gpW/kJaZcYKl/mvSQiPDba8iaCMSU0hgk4N/
        cwE5Rk4gKdUeX+/KH6iqrgNFP0R0m1Iz8lmy8kmyR93AJxKe/iMo85p7SUrJsNXh2moWzVUT+Qha
        hlxTzr5fJigMv9Q+obO/3f1Hqw5ecnUpBUvD52Zx9TyZsm55qulJXhZHRSbvx89Tw6rYoq2cTEB0
        EU+TJBC0HI/LQ56ULErP6UYNtZVUW7GPAr56a7N0WZI+GzVl7siV8++OZlM6Gw07C/tJB4omBhvq
        eYlEflq5eeuc975e2m9bcUm2LxDw9cjtcmDaZResHzNoACIKrjc3ZmszHxNxKkpKK25+8PWFI7YU
        7+3TGAgkZaelVY4fPnj9vddNhBZhsERyE8l/+pN/erq6vj61V26XsidumaSGrQeDrkOyU+Ku8KY8
        PO/97fv2rQwEg1s37YpeoE9kElJIAHJ5iWq/9gwez4+vHzBaXR0GK6Pxk4keJ1vhZlx3Pzk65Nkr
        YdNe8jbVfjlf2LRbSfCnH5mgtVrNkwDHxaZIxv/N01xqZ/Z0a1ixmGo/e1V8Z4JjjuS0bEpOzaKa
        ihKqq2wabaNqFILymzRr1hhWYg/72bujV+P6gkd821ZwqwejwBUx3wh4YPfH9i+odnt4YRqOBc/C
        Y6JfV9PZEvJ+9Ay3/VPqHrmYxsqp5qPnmr3kVyBGnGqMbdmI0uEiT59h1Rld83pLE+8SmW51ElZI
        gIYgULyRHDl5bMU42FYvpZ1A7oFjSF71abNpfaMFewmkXTGDkodfxK3371hD1QtnkdJok/oFMQKT
        koyHIiZum5AQR9j4/uJNJNeKrIqCYxRJoowO+Wzt46GaMqsZVBo1anvaHSs1H4HYCLB7zFtJDdsK
        2kWgqgOavU49ibpyFnAJTEJHNyhBP/kLl5N8iK8tcOaeSK4+Q6PeKCgSiK1POv1cSr/8Nu6kBa1F
        1ev3UqBUbFQWDxxs9eQeeKZdSxRvsHfDJbeo6ZkFgmOZ1KzOlJadazsvOeQHRl0/K9xutIIEJ6GF
        BID4ev+mpUSNnM0boX7qO5IcHfPtdTHi7IAUvg+TI7uLvdLfSN4Pn6HG9d+0+n0EpO6+6D5lHDmy
        OtkrkZioroqU6lJ1AyiKkFxJqfdSYPdmChRt1ErJNrZ68tva4X0ypz5BrryT4vkxBIK4kwbNqT2i
        KkdypEw5CpcjOA5IWHODmeDBIvJvW0nuk8eqK8MmJKWSh61IG6rLSOEJElGASSvjmpnkGXCGvZJN
        UvUrPibvJy+rmg1B64DWB9ofV749BBLIVQfJt/pz1UFUNUWESdUMfNu/p8oXZpDSoCeqY7+NrGlz
        KGXsVbaxPf2GUxYTAg89O73Z8FmB4GgBjWZGx+50aJ9tKxlsoPR8XN7D6VbvPyk5jVsvV5WqPkOR
        Nl0DCBF397ZtoUO+HWuocfWXEfvjGlLGTCBXt77c+uDB3VRX8PewqdoFIYSQQKT+2Py71qn+Cc5u
        /W31DnZTefqfoaZ4VleiDbXhB8Mk1TGf3D0GHj7l6TeCUs+dpNoGrWClWv3mLGHTjhPOLr1V7Q/X
        DwFRLZu+pWBl5HTJofYNFCzd02TSR5gjvltXT0syJfa9p5z5c/LtXEfeD55RQzEFgmMRT0oGudni
        x9900TN0yNQ5eWv/ek9zOyw2i7rYgTYPiy7OfQhNXuN/PqRgGDOvQcrYqyn1gim287WfvkyNa75S
        n8XhSBp8FmXf8TJ/d9a6Gqp8cQaTFMQ9Gg1CSNCBROnbXEDJGTkkZVrU1Jj4TxxKzjwtURnC6wIH
        wsTXuz2Uce19lH7lnYdPOdKzSUrLsjVVvJVUveBB8u8ujNvnSGTwQFB3g+QlqEKipR3fsxVM68Ke
        Auy7ql74EJ3wmz/bw2fZgzFz4j0UKN5E9Ss/a9X7CARtSVJ6jlVIoCSfmqL4rXiMHyjeQM6cruTM
        P9m2OMJ9AwFCXvXJ4RwksRE5LsmZk0uZNz7K352VCRZ1SxZS3dL3xO6sUZLwPglmlOoyJigs46ug
        nS420WerBYJAeCRyZHdW8/sbRUrn5PiXg+T97BUxmcQJZL70nDKOpAzeXlkKBQ8gJHJNqzd4gtap
        fsVi8i5+iZv+WWJCZuZNj5O716BWvY9A0JZ4OKYAhZRI+y3EhLboWqaa9+xI5Ozci9x9hsXFKbzJ
        yFik/fwu8vQfya33bSygmncej1vEWiIgNAkmoLzCZAJ7mTN/YLPtW0PwYLGqNovVJlbodQwdPXnO
        guZbthZ1i153c60USWH/U5sa9u78fG/23Aibw+JBgweOM7cPt17xHlLNDIo9oUyLwHfm/eBpNSlW
        0pDzbfWwo2bd+AhVzJ1Mcv2R2HhPIIgNlyfVdk5yODgpaFsOHIORtC5p2CWqb1cTHE5VOxss36s+
        C+OBujvryEsp7bJb7b5lZIogKxMRZLEghAQLjhNyVR+EtgaqONiwvYtfVGP6o6XS78xXjkiO8igj
        n5W23564sjH86h+KR2deX1VI4PohBPzqFtFB7oqm5QSryqj6jQcoJ78/OTvZfy/JIy6m/2fvTMCi
        Kvc//p0ZZmBgABFQRAUEF3DfSkRU1LRV2tPy5tJ2S/+VdS2v2b1ZlqmVt7K6/1vdrFveNtPMStNK
        E0IFRUJBBREEFxbZt9nnvr9zBoGZM8zADMpyPs/zPgfPOXPOGeec837f97d537UMVeKoRaQDQimc
        OTNAU7u+0eTyMEhDYQ43g8eFI1uaHTy8oBg6BerKb9rsFN4Utz4RfHVWpUARN60aVZtXQ3vykNPn
        6W6I5oYmSD19oBgxnd28AjcZPUxGPd/seOVyDjE0Q9DQjMJVCb3vWQ73kXEuufbuitS3N/vN4mj+
        1Hoj1eHI+4OrxdEeaE+loPq/q4VfcHJ3qO5YynlYSwQcVkVErjZSC1HNblPr6QUn4ZzCz6QysUA+
        XNbvTSkbLCkiY7h6Ns4gZYLDe+4KuA0QMPNRJtvELajbvalVAzIRHnEmwQzVYeBi63taJxshSBHr
        CzK4jsfYknc8GzXWbN/IOpDky6sUkROgin/cqs4Dncv34fXQv3RnqwoDifDQSEQ+fCrvJyKAsew8
        F9raXi8GSsNct/dzrrKk1/WLrGYyJJ6+8Fn4MrtvTkGbm94u1yAi0tEhEU2VVz28/SFR9Wy+kZzC
        Q0fAUHIW+gttKiHBiXDltHuhjJsLIadGymRb+emLMLYUlSZiE1EkgL/J3AaMgVtf4dh6SrxDNzkV
        BLr8GaGRK8E6Dk1mElOuWy+vUqf+DFlgqDm+vjnyAaPgu/AVlG98TAyDbCXkrGisLBJ2jjIZYbiY
        7VDOAhJ01V+tt1qvP3fKrqmAfA5oNoFCJYXjwk28OUIUCSLdGGNVKefI6D72etbrWBddI6djgvyG
        KOLBVF1q81gy/yC2f+zlRGhSJjy4gnmWfg/g/ZEo1b3+gu1qryItI4oEmGPrh0QLOrvQzIA2I6GZ
        QGgtxuoyPr4+YiTcgi2Se0ilUE65G7qco6je9qbd+PqoiGC8eotw7YeuiqdBDaRYR2ZRUhZt5W9O
        H19zbD/X2oq+OB9Vm19y+jpERLouJhjOn4LOLwjygeOtCqdJfALgPv4WXtwX50Fz5EebR/IYfyMU
        w6c0fpYizzytK+qSP1L1NxugPrLHZd+iO9LtRYLUuyfkw+OsvW8Jiq0/c5SLdnAWLr7+oxXwe3qT
        9Q3NbnKyp+kKTqL+4I4Wj6N0l6Nf754t7tPVkGvEaUIRkc4Omef02SmcH5GsV6jFVkljWXeu3koL
        fjxsP6llCXirk5mgTtmJmh3viY7DTtKtHRclcg8ohk4WzvHPMJYUQJ+V7BKbtolLv7wDtTvfF46v
        V/nBd9ErkPePdPpcIiIiIh0RMv8ZCjLtO387CflB1P3yH5iqxYrPztJtZxIoBEgeMYYLnxP0Q6ir
        hDZzP4wuHMWSoq3e8jrkA8fBfVSc1Xa3sOGcUCjb8CBXglWkCeQ30qMfE1hXf1RArzdjXQV7EVV3
        iRK5IiJXCqlXD7iFjxZMUe9KJB6eUM1eAk3G7zCUtZz+WaRluq1IkPWOgHxwNFfp0QqjHrpTB2Eo
        Pe/y89INW7VpBfz/tgVS/74WWyXwmDCbj6/fvFosPmLGJJcDQydC2Xdwi/uVV9VCrWnu0yGTu7s8
        BFGirkPPwnToco9AV3IaJm2t3WI1IiLdHS6CLCqWy0VjjYkPF6fniDMPtPA86dQw1jcO3jifBC9K
        8dD0OZdAMWIyvOc+x963z4lJzZygW4oEqU8gH1svZNei2PqCTOjzM9rt/Nqsw1ySHd+H1lt7xLMH
        SXXr49CdSUfd/q/a7Ro6E3qpAoUDJ9ndb+Pm3Th8vLn/SEBIBKQtptFuPQqZFDPCRuP6wZPhc2If
        u1fSoCvO5sWCS88kItI1oJlbt4hxcOtvuzqr7vh+NjBSc03IJNuAOmUX55DYGN3ghx6PvQVZn/Dm
        O7IBoOqmR7gierU//EsU8m2k24kEUp3ysJFcTLup1npK31RfzRVwsuvsQmKiKB8yiwIlXPiOnXhc
        8nGo2/MJl77XY9xMwX08r5sP7Ykk6EvEFKKOwuW7Mlmvc/W7QaM34sccIxI8QjF98AOYEJKJfhdT
        ock+AF1pLkyaGlEsiIg0QdorDIrBE4Rnbtk7U5eRAH1hjkPHotlYbebvlws00UxhlaoHeix5x7qQ
        HhsIck7heRnQHE9w9mt0S7qdSKAOWnvsV4CarX0c6FXIFFDydKyAbc3EZfiyByX2qHhnsVUoUJOL
        4HIuiHRcqtUGbM8yIFEVhdG9wnFj6AQE5B+CLieFN0OoSSyIckGke0PVGN0pgkyoOit7x+lOp3A1
        c9oKva/rErZwSeu8Zlu/U2WBIfB94FWUvTpXHHS1gW4nEghXTTuZnOzEeSUslivt7JTW6PBLjRRJ
        inBMCR2CW4ZdB6+MX2DISYaumHwWasSpzk6Ekep9aGqh19YzvW9orBxK2VYFnnne56Xzpd62fH+x
        OzSyNcXj1iYWBi+1UwJOYk6UJPHtJbidSrdTCXenq7NSbYYv1kAePgqK4ZOttiuGToTPwldQ8e7j
        MNZV2TyO1iRVxu/WfzTx/vVX30PaRRhhKofEVMakU57E4JaaNKjmKFatcjhkr1uKBBGR9qBea8BP
        2QYkKgIwc9AixITHIqggBdqsA5zPgrG+QpxX6KAYjXrUV5VAXVMBvQuKDXVSeremeNylen2LdWK5
        CLKB10AWFC64navOeiLRZQ7ahtKLqNy0Ev4rv+RqQlhcDDzj7oUuOxU129+2Kdr1Jsg1RtOtXek5
        5eSrScK9e0xSA6JzlOWYv+47g0myKeXTZ+1mo+v6IoHdqBIhO9hVgTchdKUbUMSaWq0R32bUIME7
        FGN7h2BmaDSCzh6ANptmFrJg1Iie1h0FGsHWlheirrLoso1bxHlodkXWZyCfXXjWx0UAACAASURB
        VFHo/ctVZ01quQ5OG9BmJnEp1n0WrYHE3cK84SaH95xnocvPhDq1W2dh9GOd0AIZTAui71/3m5tU
        9pfET5YdsbWzvd6TYs5sFCngoLedkDGJjELkjk6urKQ1ySOFFItaYF9HoOucaD4e/fIFrFEeXdsJ
        vgmVLzyGT4P7kJg2ntaVmGC4dB7as0ehL8+HUdfW/4rWY9DrkZ19yuH9I6OGWa0rKryAw8kHUVJU
        iD7B/TAhJhY9/JzL/Jhx7A+czDyG2poahA6IQPSkyXB3b+l261yUVmuxpxpI8ghGTN+7ET9kClQZ
        e2E4mwaJkH32KuIul+HGaxpDco/lliPnonXdi0BfD0waJjx13Ba2Hyi4aqYYnaYOlUVnYBBDjV0O
        H0E2zUZ1ViP0Z9O56qyu/u3JhFK78wPIB42F5/Q/WfmMSXsGc1Fl+tV3QX/RMUfJLs5UvdGQzMTC
        q9Xq+pcyvl5lZWaxJxJSWGupxjh5/82wWMekIzaxZlmz8yJrj7G23c45LbmVtXdZs0wqQL3s26z9
        jTVB+5FHUNgL+hGGjUy2tvKUrSP5nDpw09Hib5uuiwoPxt3XX9u4gj0LSk0V3I/thyIjAdrcw0ws
        nINJV9/uMwsVFeWYfZ3jQin7fGOhKZ1Oi/WvvIBPN73PiY0G5HIF7l/0CJY99wL3d2vIPnUCy596
        DMf+ONpsfUBgL6zd8B6mTheO+Ois1Kr12MPeRwlyf9wwZD4mR8Sgd3U+U15X+8oa8VDIsHBmY12R
        D3dlCYqEPj2VzfZzlh0HC2C4ChpBU1vOBEKu6CvSDlDxO746q5/gdmPZRehOHmi36qzkFF79+Suc
        fwJFkFkiDx8J30VrUP6PB8X8CTw0qF/prVRGx9296rZ9X69q9p/SkkgIAS8Q6Je0NWIvt/h3P9Z+
        Yo2GmIdZe581MvBR+cPbWdvC2nXgZxUcYRZrW81fYru5kSCIZu1R1p5lzZ+1h4Q+LImIymKLLAfP
        1WYmzt/Q12RqnsRHGWiCxqN5OI5G6Qu3qfPgOXwKPE8mQXdkD3Tn0qErzWP/y5p2EwtSqZTrgFui
        sqKCEwRBfYKbrX/+mSex9ev/QuXtjUUPL8GQyGHIy83B++/+Ax+9/w4qysuw7s1/OnwtZ/POYN5d
        N6O8rBTXTozFnXPmcdO83239CkmJv+GxB+7Dl9t3Y8SoMW36rh0Ztc6Ib4/XINE7BJ6GABTqZPY/
        JOJy1DVlnECwhZ+vD4L79IJ/Tz+ovDwhd5PBYBBNEZaEuWuA08es1ssC+kMilcF4Kd9qm8lg4M0M
        avudM1diXaDwmv58lt24Zv25LFRtWgnVHUshkVk7Tki9/aCImmhldnBzc8OsabFsBNpRTNSuQafT
        o7yyEkXFpTh3sVD4fjZhhtpD+dOEeatuPLR51WXvzpb+JxokGP1KlrMFtqBOmwRCKnhzQ8MIn0r4
        fcjag6y9zto1Dh6Peh8SCKtZ+3uT9XS8H8yNjvkOa2kOHvOqome/TZVff9RG3wWf4ZOh/GMvFH/s
        gzY/DfqyszDqXT/16dfTHwfSbNdqP56ehnviZ3JT/R/85+vL62mkTwKBZgo++eI7jBw99vK2mTfc
        jPhZk7nti/78f4ImCiGeW/Y4JxDi77gHr731L07AEHfO+ROeWvIgvv92C9587WX8+7Nv2vhtOz6X
        qumx6BovobQzZaioabsjuGVei/ZGW1+FquI8wW0B/n4YMyIKvQP9r+xFdVK8ZMLh2/oL2Vxzlqov
        13KtLdAMUf2h77nWGsg64eujgofETthGJyQwwA+DI8Kg0WiRmZWDk9lnhMRCDCQen4Af1HO09KZq
        6MiPtrCPJRPNSzIPWL45yDRAHTqZI8hQZc8oTyIl3LzfGoHtu1hLZI1qht6CTiISGjBIZCj3DoZ8
        0lyoRk+Hx4kDMDGxQAl59BXnYNReGQ/rqqpKLHloHjeL8PL6txE5tNFK9MN2vqOOmzGrmUAgwgcO
        xuix43HoQCKSWXNEJGSdzOT29Q8IxOq1b14WCA089OgT2PvzLhTkn3XBNxO5EmxNzEN6ruWEYsfE
        aNCjsijPysRATnZjRw5F5KABLk/hLSLS0XB3V3BieEBIPyQePIKKquZmRfYM3BY9b+3jBzf/dSP9
        uyWRMN68PNyK8zcYmYSO29r5OjrWv8GLDVuCoti87LTSX0diQdUH8ug7oYyMgdfpZOiSf4KuIJ1P
        yEM+C+1oN12z6jlcOH8OsVOnY868Bc22PfnMStwUfzu8vFSCn5UrWueLsH3rl9wy/vZ74OnlZbV9
        2IhRSDvl+noZIiJETdl5JhSamwVJqE6ZOA79goXqCYiIdF16+Hrjhhmx+DXhEIovWVTLlErWTJi3
        btuhzcvPOWJuINPBzaBpCIB6BTLmbQPviGjJz+D9BchB8WM0n014xLwk84Ujrv2ZsOFrYIauvUHI
        WBvGOhk6gwk67yDUjpkNn6hJ8MxMgO7Ir9DmHYH+Ui6MWtdVo2wgPe0ItpnNCavWvGG1XalUYuTo
        cYKfzc3JRsrBJO7v2CnTHDrfyczj3HJi7BRuqdGocSwtlXOsDAkdgMGRQ9vyNURE7KLXqVFfdclq
        ffT4UaJAcAKJRAqJu6pjpJJigymTXu10krvuBPlgxE26Fjt/SUB1TbM+RiWR4AW2fNiWSCC/gn7m
        v8lIbekiSj3KcvAmhKasYy2OtVjwkRE0E1APXmRQlAKN/P/cpm9jzcOshYEXHK0zPHVgDOxxK/fw
        h3xsPFRMLHgcT4Tp+H5oT6dwD4ArS6yu/ttyGI1G3Dd/AULDhBOeNKW46CLy83Kxf9/P2Pzxh1wn
        /8RfVnCmB0fIOc37kAb16YuPP3gPb72xBjXVjVNdNJPwxsYPEDFoSNu+kIiIDWrLrMc0Yf2DER7a
        T2BvEYdwU0AaMQqqwJCrfSU8tZXQZR2ErugkDNUlTmdx7C4oFHLEXDsGu/f+3nzWWoL5Mfe/ttKW
        SBjd5G+KY1kBfrROkpsyck1l7S3WaO6uqWs7uaySIKAohDjzPg1cYG06a44H7NuGZjVeN/9NIZDF
        LezbKdFBinJlIOTRd8AzaiKUWckwpCdCL3NNRcPDyQeQlpoCGVOSi598xqHPbNywFl989vHlf5Oz
        4SNLljp8TnV9Pbf8+MN/YutXmxE1bAQmxExm6+uwZ9cPXN6EO26ehu92JzokWkREHIE6C41FMTeZ
        TIpxoy2jtEVaQ6FOjq1esTB5dowwUi+ZCaOGTEOvM+w9eSIJuouZTCwUi2LBAQL9/Zhg7o+cvGYR
        KQqTxHSvLZHgCd4RkFztb2Ct6RNGORDeAz8jsJ61z5tsJ++2naxRvN3vrP0IfqRP88uzzce8h7Ud
        TnwfMmdsN18jmT02OHGsDg+ZISpVQagZFw+fYZOgqay0/yEHePfN9dzyrjnzENirt0OfGTp8FJ5d
        +SKqq6uw49st+ObLz3AgcR82b/kR/UJC7X6ezAoECYTFTyzjfB4anBeXP/8yFsyNR3paKv761GJ8
        vm1XG7+ZiEhztPXVVh1FWEhfKD0ESsWLOAw5xlej44Tx1rDr2SMJQZ9BczByYCx6ZO6FIjcV2nPp
        MNSWwmRs33w5nZ2hQyIsRQJFH91powQhN31PgerUIVvWU6anbRn4WQPyaLvBvJ4iFigkkQQCjfLJ
        5EBRCdSJ38bafeB9GihXwsA2fg+apaDA1gDwQmEuukmFJEo4U+7uj7pezo+wyVEx8Te+CubChxY7
        /Ll7738ADy9eiqeX/x279iUjZnIcd6wnHl1g/8MML0/eWZFmEJoKBILyMLy+8QPub5rloOOKiLgC
        EgmW0KhJpOtBs+UX6mXYpQ5B0uhFKJq1FB4zHoHHoMlw8+7N+VCICEOhn+TM2BQJTBPaGqxNAoFm
        BUgINBikbwJvjiCzwgqBz5BrOwmFeNaoZ3q6leekeW3yhaBfmXoTSqbULQSCq9n5/TZuSY6CAwdH
        tukYlFPh5XVvYXrMKC6fwskTGXbDIN09mI6sqsR1199sFf5IDAgfiL79Q3C+IB9ZpzIR3Fe0F3d0
        evspEVans7+jAHlFVybbHVVzbAqZGmh6VaRrk19lxAVZOAIGhWFE5HQE5x6ANv1XaM8fh6GmRHRw
        FKBP716oqGwmqhXOZHSxzIMQZV4ehO08yGRmIJEwohXnod6ExAGJBBIFJEDalmFDhKMh/wGFIjpD
        /9AwLudB6aUSFJzNtSsS+oeEoaS4CAqF7WnehnBLrVrMp98ZWDI7yv5ONrjtxV9ceCW2Meiav6p8
        VCpBkSrS9dAbTCisl6BEGoTA0NswZuAk+J3YB9PpZGgL0mGoKoLJ0GWqQjuN5UwCYUskUAZDKspN
        aZXftbFPg8ngtHnZMJwQDqrnaegdWvOE/j/4SAb6JWkmouum4rsCUPIkchAkps6Y1eK+Tz66EAeT
        EvD8i2sx+/a7rbZTLYf6ej7pk61cCk0ZPmoMUg8fwqkTx23uQyKC8O8VhILCMrvpV//H3nmAR1Wl
        ffw/Pb0SktBBICQQeu8LLopSbawiZUEUVlZd93MVFUEsa0cfdGVRF0RUEFD2A0ERkCZFegmEThIC
        IYVkkskk0/e+Z2YSMvdOSWYChJzf89xnbu4999wzuTNz3vNWg9EMk6OmRLGuzGNbTv3E1RZNyWQ4
        9QuLVRAW9OQwF4fm7R9BmzYDEX9hN6wndsKYfQwWLUW/3BKBnDcVtUqcadKdkEAl6ijscSLs0Quu
        an2aXSjuhZwS1zuOOZMukZMimR1yJPp1Ll1/93HM5PswzXEfqvqz08frOG44eugAC3uMiIj0uvIP
        Cg7BtYJ8rFm9XFJI2LxxA/SlpSzPgrt8CtczfMQYLP1iIbZs+olpH0gL4cRoMuOr5atYymZNSDjm
        r9wHmcxt9VIOp8ZYeEnoek1GoQnZigTEtRqLlJa90SRjL4zHtsGcd06QE24dR8ybgVIpfv/uhAQK
        XZwsbFTGkFT7L6LShEAJjL527JNTotOxcauwHYVduKDcClTUyRmaSPeZB7sAQUtPV+3EUsfrMmHb
        6NhvIWxvOPZJs1EMcb4GJzQGcTURjogTx4+yV8pJ4I3Jj83AmlXfYvuvm/DFvxewAk9ONS2FT778
        /NNsf+KUJ5jjoRM69/WXn7N9qs/gpHvPPqyoE6Vmfmr6ZPzr82WQq4KxYcdRrP15Kw79aP9YxCf1
        5w5GdYRXlh6sM2mZORwnZIa4ohMmKHkiGjQdiW5khji1AzZzzfxrbmfcCQk0k/xN2OYLGwXR0zKS
        lnUUuUCFm+gXnLzfXr3uGhLPKWHSDtgdGjMc+zSBU5QEuROTRoBMBq6u6xMcr6SNcAoJM2GPhiD+
        z7G5Y9l1fXA84ExolNjYu3c3RSG8NPefeGPuLLw172WsWLaE1XbIuXIZRw7tZxqJYcNH4u+zXqly
        3aWsTEG4WM72rxcSCEqWNHHcKCYo9OuWjPD4VjCbzSjOOcdy60c1aovE9gMD9G45HA7HPWSGuFom
        x/qyBmja9kGotFeF1XD91SZI1S7x5LhI2RQpgRI5ClLypBaO4yRA0Mqesim66u0uChstUSnB0TjY
        TQQEuTGTduF1x/WuOI9dnzc10k1bKbgWwUdoxU9mBteCTe6YOHU6Wicl4+P5bzN/ggvn7S4opIkY
        P+kxllDJ1QnMkymDSlF/t3Yznvzr0zi0axPyM9LY8aDwBohv2wuJyQMCmlWSw+FwfCFLS8ryOlsG
        qNZQGo/uft908sCztjIWjpQH6bDCwhxtiTwuPNSqkMuF1b2NVvkz3XVqg0wv/MwfLyzVpxtMFllC
        VDjpcKJQmSWRMEJmc1aVOOJ4vRuVeRfsx22yq17fhQ0lkDk1DcKEFZuYGzZywlLPF92+NMrcB9uZ
        g/QcYFNWddL6eGgyMNThkb5tCZuQLapgj/2NEgTrES/OgNEyDVpdKSJCQqBROxxcDv9Y0c6m1MAm
        V2BUnAyjPnzNfvB4VQ92s/B8Tp7KxvRBvQTRsxfKDQYoFAqolJXyqlWQ7ovNTsFD+CQplDioVeLs
        NS9eyDYKabo1sr9xOBxOXcNsEYeFKq35V2DYvxHlp7fR33GiFg4ovaGj/INv6fkEFI7riqs3Tr+Q
        B0UguNf9lMOh3goJ1pxM6H9exGKBA02E49WfAMXu3ptUQd0kFeWRY3GmyHPErkwQLuyCAofD4XCq
        i1TFYfara7OaYCkLTLrfm45MLrwf7r1MVSNvl2dqM/lSNJTD4XA4/iCXMPVyF3IOh8PhcDjM9OuK
        W/2tTK6ATBPi1onMZiiDzeI9XEQRkwCZUpy8xFpSCKtETnVfr2djMJbDUnTbFYCsNWTqILf/S1gt
        wjPVS6qbqvShUkMRnSA6brOYYRWeBb3W5Hp7Jzbhc3EN1vJS6fMcDofDuaG4N/IKk4m601DIwyW8
        PYV5xJydDtOpPV7zX0fN+AiqZilVLxcmg5IVb0H/6zcer1U1bYeomR9DESV2g6DJSLf6A+g3f8Vd
        1XxEEd0IqpT+gqAgzqplMxlgPLYVlgLPhZWUTZIQ+4L4uZnzslC04C8wX73o9loKrwn94ySEjX5K
        8rylIBuFH03nQgKHw+HcIrgVEmzGMpgzT0DT/R5htg4SnVcFh8FaeAXmnPOeb9CoNZQtXOq2C0KC
        PMJzqIlc6D9iwhxoOg+VPG/Y/zPK92+QFBB4AJ00lvxMKEoKoGwuLp1B/zN1ygCU7/2BaWjcIdME
        i5+n47hM5bn0rqptd4Q/MhuKOIkcDcI9desWwpLLo1nrEv94qCPMlpr7AO1Nz8On69IDOCIOhxNI
        PLqLW3LOwnT+kPDj3os5BFZBHSysSgfAqs2HtSyw8Qtk6ggZ+iiC+4yWHlduBrSLZ8GizZc8zzUL
        0pD2xZS+SxDQGkAenSg6L2/QBKo2PWA6uSvgFdLk4dGInDBXEBCkKzvqt62A/pclgvzInU7rEmFB
        /tSIA0I0/l3vD0ZDOXas/9ZjmzapPdCstV0oTtu/HTlZ53zqu1nr9sK1PX1qS5/5Y79vxYkD25Gf
        Y9fkJTRthfbdBiK5a3+f+uBwaguP31CKEjCd2Q95VAIU8S1F5+VR8VAl9Ybx2K8++Sf4iqp1V4Q/
        /BITRERj0hejeMnLgvByROJKOwarLLjXxHfdpXD2EUsEWdAr7gt5uawiCtRlTLA0dD2mLzci60qB
        17uYzBaUGyv/d+RdGhrseUXujTgP0R1WXSFMaduh6SkIYGoXDZEgnKnu6AZL/iVYrl7wawzXQ+aN
        sFEzoelKubXEeh76jBUvm8fNDJwbSk7WWfyw+F2Pbe6b8o8KIWH/9h+xb+tan/oeMmayT0KCvkSL
        ha/9BefTD1U5nn54F7auXYaOvYZg6vPzoZAwEXI4NwKvYrzNUArT8W3CSjAGspDIqidlcihbdGS2
        ZHNWWkAGpBDuEzlpHhQNJFacwuSn37wM+q0rPIY5XjIok2Q2q3spwidkLn9Vb4WbdvYSXvxopX9D
        qCGrh4V5DFshTYzp9F6oUvoJgoHLR0AVBHX7QTCUFMCqD4yGSJM6CGFjnxEerviHzlpcAO3il7ya
        rTi1S2m5GXO/qpyosgv0ku3O5+iqtPOXQt3NK9Obde4Ee23cIgntuvSVbNOsTaVprX33gYiIbuC2
        v7wrmTi6ZzOb0Dt0H+TTGL6c/zwTEOIbt8QD02ahbcdeKCstwfF92/D94ndwdO8WfPfv1/Hwk696
        74zD8RMpLbxPuj6r9ipMJ3+DupOwEnSVaBVKqJP7Cj/2uUI7/5L3kJkhdMQMaDoPkTxvTNuJkuVv
        BlRrUR8h9abp3AHIYxtBkdhGdN6uIeoD45FNfpsdFMI9IibMZUKmCJMBulXvwXB4i1/34PgP+RUc
        Pn/NaztdmcmndnWBC+n2dUTPIaMwdMyfvbbvPvBetklhKNfjrafvY/ukfaDJ3hskpJAJQ6XWYOa8
        zxEdZzcBhkXGoPedYxEZ2xCfzJmGXRtX495H/upRQOFwAoJEdJtPeRIoGoE0BebMY5KdyMJjoW7X
        FzJFze2L5Pmu6TIUYWOeYpEVrlgLslH81RyY87NrfA9OJTazkZkdbMUSfh3Cs1A2aw9Fo7Z+OYGS
        I2P4uOeFz4bUD6YNZXvXoXT9Iq9hkxxObXA54wx7bdoqxUtL73y38HWmSejQYzAGjRjv0zVkUiDa
        dOhRISBcT3KXfggXBAYS6p1aDw7nRuPzrG6zWGBK3w15ZLywAm0sOq9IbM1MD+YLRxyChM1jzL1M
        Lq8iVMijGiJi4jz2KsJYjuIVb8NwfKevw+X4gEWbB+OJHdB0v1csmFEIbEp/lBfnAiVUCtjz82Qo
        FFWeaVDP4Qi9awrTNrlivnQaxUvnwFJye6xKOXULmnivZNqFBHIy9Aea7PduWQNNUAgefnKuz9d1
        7jsMcYnNEBIW6baNJcAOxByOJ6pbBVIEJT8yHt8KTa8xkAWFVj2pUEGd3A+KmMYsfz7ZmC3Zp9yN
        BMGDH4aqVafKyxs2gzqph7it8GXWb18J/cbFPq84yfGvR6pYjV5fUCpzffagsOScg+ncQRbVQI6L
        1yMLj2ECBGkbmJB4ao/bfpiQN+k12EodqaAFwUCT0k/4nISJ2lKb4i9nw5x50te3xOEElKuXLsBk
        NLBJOuPMcezYsBzZF9KFr4ASjVsmod+wB5HUqbfXfixmE1Z8Oo/tD//TDETGSCxy3ED3ps0d504c
        ZI6NMpkcTe/wX9vB4dSEatsHSO1vOr0H6vYDxY5omlAomtmlcqtBLwgJp932QypoaTV0VSiKofjr
        eYKAovN5jOFhIbi3u2/hR7cjmoyfUeZjWxYWeeZ3lgVR3rCFy1kZ5NGNANosJpgvuq/cLQsOR3C/
        +7zfULgfmRjKdv+XhztybhrZF+0LmGt5V7Bg9pQq565eOo+DOzZg2APTMGri3zz2s+uX1czMQP4C
        g0Y8GrDxkfCxctHrbL9T76HcH4Fz06i2kEA/7OYLh4VJJRGKprUr3bJwR1pxXj5bq/ep71A6ZiOF
        RYZRBEuE9wv8wJj2G0pWvgub6eZ5tXM4mWfs0Vj0ezZ83Az0v+dPiIyOw7Xcy9j0/RfYvv5bbFz1
        GVvp9/nj/ZJ90LWbf1jM9oeMnsQcEAMB9fvVhy/i0vl05pPw4BMvBaTfmjCgQzwax9q1xqt2XhQl
        zooJ12BYV7v5+WRWEY5IOLW2iA+DRmXXUlIUzaV86VDnpCbuzS7Vhe5B9+JUD8lS0TXrSiZpZw44
        MjlkErkSvF5WC0O57SFTg/wG1Pui6BjlzUugw+EQ7Tr3ET6KKjRplYwu/e6qOB7TsBEemj6bqfi3
        /fg11i77iEUayFyTyQkc3bMF+TlZCA4Nx4B7Hg7IuEiDsPi953B410bm4zDtpQXVMmEEmpYJ4QgP
        VqGkzCSZWTMuMgixEXbhqMwgPSn3SW7IhAkiK6/UrZBwZ5dGARo18P97MrmQUAOk/M6qPSvQl0XV
        uhsUCXcEZFAe70WpmR99BSqJNMCe4BkXq4c8KBTqDoMk/QcCjTqpJyLGzRLuGVLr9+Jw3EGZDEdO
        eKaKgHA9Q8ZOZq/FhfkVURCu7PplFXvtMXgkm9D9RVdciI/nTGMCQkh4JJ6c9xlatevid781JUhY
        /ZOAQOQWSRswmzSo9E3L0/KS7nUdqVLR1V7SURQDS9MsF5eUhFEPS14Wcza0suqM7qdr09mDMGdX
        fvkoeZI6pa+o6qSyeQdETn0Lhe9M5J7wtQBVhVS1Hwh5jJQUb4NNeI5W3TXmS0D1PNxhK9fBcGw7
        bHpHZU/Kn5HUA4o4F8cs4XjIXVNhyjyJ0g2LmEMkh3OrEduwMdSaIJa6WacV/+6U63VIP7yb7Xcb
        cI/f98u7nIFP5j7ONBMUDvnk3M9YauabSVxUZUbWnELp736DSLuGgLQMRaWBMyGWGy1+aQJMftQT
        qc9Uq1S0FJTzn1acUgWfaBIxnvytMgRSEBTchswJxylzom7tvyoHF52A2JdXQuUa4SAIDUFdhyHs
        wedQvGyuMFEZqjNkjgco3IWKPSmbdRDX5gBFIRShfN9a2HSF9r89hGNZC3Oh/eIFFtroJLjvGEQ/
        s0jk5yATVl0R42fDlJHGBAsO50ZTJgizOm0homLj3foSmM32pG1KicJlaQe2M9MATeh3pHT1aywZ
        p4/h03nTmSahedtUzHhlIcIiov3qMxA0iKj8nc/Xin93FXIZosPs/5urReVSKXRqTPolLX5Luxq4
        Djk1xmdzg4zS9XYYzBInibGx0tHmC0eZtzxNJt5i6lk7k6Fis+RlCpPM88JkkyNuTLn/R89kBZ+k
        4jg5NUMe1xyqdn2ktUKmchiPb4OtpMD+PL3GawvP22Ss8kwpgqH0x0VMgBTdOyYRkVP+CaVURUgO
        pxahlO4vPNofrz5xN0t/LAUlL7JaLMy82qi5OJzaeV3r9t39GsuVzLMVAkKnPnfimTeX3hICApEQ
        U+kPJmVuIAGBBAUir4ibGm5XfBISKEEOFXKSKvJEUDpmStvsT7pkEioMx7ahZPUHLHmSaAxBYYic
        /AZUbbrV+B6cSuShUVCnDpb2Q6C0zRePsjwXXhMoeYBKTpd8/z4Mx3dInlcn90bE5Ne4fwLnhkKJ
        3No6ii/t/Gm5ZCju+m8/Ya+pPQczx0RXnBkQ23WWrvngC2TKWPTGTCYgpPb8Ax574cOARUgEgoYO
        c4O21AijWfw/cpoaiFytr0HXnLqGV3MDyYmUnld1R1c3K04DTGk7WHVBfyEJv3Tdp8yWHTzgQdF5
        RaPWiJz6Nq69Oc5tmWjnmDnuqfBDiIyXPG/NvwTz6d/9EhCcWK7lQPufWWgwZw3kMQkuA5EjZOA4
        mM4dge6/C3h6Zs4NY8T4p5hPwakje7B0/gvs79j4JiwEkipDHvv9V+aMeP+0WaJrScOQe/ki209s
        5t2Bm/IufPjiJLb/zJtfIr6J3ddgy5olLMcCEREdhzVL3nfbR49BI9GkndND1QAAIABJREFUVbvq
        vs0aE6xRIizI6bQorSVwhkZ6asOp+3gVEuTRCSw9r1Q9BeHbAtPZ/bBcDVwFP0qaROl6Vc07QNks
        WXRekzqQlZGmiccmoXEgeHSDe2gVpWrVBUpB8HN1EiVslFUzbTus5b4nr/KG6fR+FH/zGiIff08c
        0qoOYs/TdOEoyg9tDtg9ORxPkO1/0t/fxjcLZmPf1nVsUyiUsDgEVUpe9Nisj5gDoyuFBTlMUCCi
        YhNE512xCG1Ligoq9p1QKmcnv/38ncc+KHV0bQkJo/s0qxKl4EqbxhFs88SjQyqFpW+3nse1Eu47
        VhexSiwMPQoJMk0IVBQaFyZRwU+YilnJYUFI8LdSoCvmrHSWRCn62c8hC42qelL4IocOnwbTxTTo
        N/7HY8lojhgyGZHpSDLPhdnEUi9br10O6D3p86HftBTqtj0QcudEUT4GeUQs0xBZ3h4PU5abVN41
        vTdXK9V7khIiEGqrXFBERqrQWFGKuD8MRffUjtjy02pcOHsSpbpihEdGI7VzLwwYMhLBIaGwwAij
        rernNSpYg4emPMv242OiYBVaGWwSWlYHJHCM/fNzFftO+t89zuf30KTljdMicOox1RESqGwzVXZU
        xDWX7qtUC1PaNo9hcTWF1Nxle9ZCtW4hwu//u6g8NdWNoPwJ5sw0GE7sDvj9b1fkgrBHzqdwk6DK
        wpxPj9RKumSmIfr6Vahapkr6ldAxKvBV+MHUaqXg9g6XEuo7j3cMQ0rmAVgNjs8VuU7t31RxfjzN
        v+2u/53LBk4u9NjnRGfzg+/4NIYnWgAGZQhsGUsrjt3fWtzOqAyCVSYhcOi2AOn2kuoWTTgym/bF
        CWVgnH4pv4Hr3ED+CM4siZQAyZUgtYIlUiKKdEaWbMkJDz+8vZAUElhoXNMUVtVRKjSOvNXJUdGq
        za21gVEpY93386Fu3RWabsNE5xVxTYXV5zsoeP0BWAp5qIw3qGwzS5gULp0D3lqUA2P6LmHVX3t+
        AZaci8yUFP3cl0x74Epw71Ewjf4fe2cC3lSV9vF/9qZJ96ahK4VSCoWybyKVTRShKp+ioo6K6DeP
        Cu64IMK4oWwjDII+H27IsMjoaAVHcRAEK4hSKFtLSymU0i3d1zTJzfLdc0Kaprlp0zZtabk/n2tS
        ktxzCzf3/O973vf/Po3ar9ey//7tSYLlWD4hybTNRCbP9YVZp4XuXAqYomu/3bLo6tYSclV/+AXG
        AH6eEQlHMpyv4/NnxLIiAahkBQBxL2zO0OgATE6wLrUczSxFTlGNR46Fp3tpUxdIU5UGuqPfWj/Y
        7DUSPiaNntxJbKvauAgCRbP1LAtZUmi9A6CpqgSVG56EOMJFR0eyfsgnu7mH2Qzm4gnad6M5tLF3
        Q61byafGK1koWzrTeR/shdhUdqXFz5JxdGn7UL48iT0nuH3a6TG0M2HSwp7ggmYfNTI6iGV89QSP
        hf7H0zreMjEUXtapwZWLYp+AlssjO8qI/oF0aw9E1HBFP3jaB6dIIJO/hUQJqjs+gP5cx5YDSMtp
        svF0DHJHTXJIOoq5vhq61J/afxyMgT0nXLec7hjOUS8dKzq8OHNqeHh4uLD1YiC4EgC2pQYdY3JY
        auDpffTKTjv8KvR1Cg2Vkc1+x2jQ1sBsNkIo7JWnOk8HEHr7QuinAucVw2yCqaKIFbUtl/YJJFLI
        RkyHoJmdLVkuM2Qdg7kVK3mhTA7ZsCnED9f5RRJxzc8CU8DdO6KzCAuyR940HCJBLBI2Oi3yJkq9
        n1555eSDitcxJIfGYq+2IUmY2ioNlIHOpWw81zsCSAZPgpC6yDYTCuw5xOScsJrEtVC9JVT4IfCl
        L2glWFPIslnFu/OgTz/senRWGCjuWATfB17n9KAxaXJR/vbcNv1GnkDtb11KIOVwXHbMJIpgW7ru
        jKUGwtnLlTiW5doLpyX0DN8Ppr0wRuflezH5coh8QuAVc2M3HJIzpFrCWJYDs67GI2Y+1wu6Bi28
        5NYLFfFCkIYlQBzcvQ1irFhgqimBsSKPve56rgGMy9EEIggsjhcJbVUJvHwCIZa0ve04T+/FrK2m
        Jb+y0bdx9KORUAM5aizWog+MgFZbNRcJQqOB23yuCbKhibR6q3lvEwLJEar9ag2MBec5Ptm52JYb
        KmsNnO2h1QH2v6vCis4RCUaTBVoXrad5Og8zx7+3WBze/5hs4u1bZEzXml/sz9POY0yWxrNN4e2F
        2OhwyGrZu77sP6DP/A1MKSsWGqraHBnoDcsNWz5chS8/+wB3zluAJxe/xfmevEvZ2PrRGhw/eggN
        2npqBhM3ZAQ+XvEGwu58pc1j1lRV4GJ2BspLimE2myGVyRCk6oN+sYOhULZspuKKzOxLGCqsgPLi
        nzDknQRTeQUWYyeeaySSQKMJ9pOdRBOqii4iKGIQLe3l4bFhKsoGk6Pm7mzLCgfJkESYa8upoPAk
        Ir9g+Dy4HMIADtdTEv3a9wW0B7Z3iQ/MqAFBCPSxCgPSKpgkLhJkUiFuHuncHVbdJGkxIToAA5sZ
        LR09V4o6HZ+n0FsQi+OGf8k+ftnVA094aFUS+9AoEqLCVFgwLA6SgEHwDxuJyCE3wfvMAWrWxGiy
        YNZVux1Z6Onxh3Onj2PXlk0tvifjdCqWPHU/9LoGBASqED98DEo1RfTPb7w9CY8uWoL75i90e8yD
        PyVj7RvPw8gw8PULwIBBCaiprsSFzDPUVGbJux9i3KTpbf5dPjyXDYVIidmxc3BDxCgEFZ2C/mIq
        TNUFMLey3tteLEIJBCZHIWJix6osugD/Pv3ZuYAvieSxQiZhJvtPiALDIAyJdnqdOM6KY8eCYa9F
        npqwBaRh3dzFNJLAhSH9MGp2rewym/JIlYLTcZHYMsdFcFch2YhWO/d+OXGhHOBTFXoNbneB7CoY
        kwWlAh+cDBmP3BnPQnDXq5BPuB+y6PEQyf16fRdIbX0tVr6+qMULEnltzbJnqEBIvDkJX3x/FCs+
        2I7N/zqARa++S99DIhFXci+4NWbhldxGgTB91t3Y9mMq3t20Axu3/Yjlaz6ByWjEilefQFlJUbt+
        p9ySWmw6XIAlFwOxK/AW4JanIU+YBWlILHvBlHVC5EfACgXndBtGV4eKgiz6yMNjg9i7G84epK3R
        nRFA0jcBovA4j5yn5PrlNWYmlLP+yul6aq4oQvWWpTCVFXhgNB6ejnPNJi6aLUCxyRulqrFQzxoG
        VX4alNlHoU8/BKbkPMwN1T0+YsDFR2uWQ1N4BeqwSPrIRc75dBQV5NHlheeXrYG0See4pLkP49d9
        e3D6+O848MM3eOSpl1sd89udn1CBQKIHi99YR3MabEycOhP3PboI//y/v+PTDSvwyjsb2/27XSmp
        xtYyIXb7KPHA8HmYHj8FivNHYLiUCqYyjxpoeQwBSbcxOyw7EEyMngoFUhapCFBDLOU9FHhAW9Qz
        mUcgHXGL8+RNjMjiE6GrKqGt0zuCSB0N34ffhEDp3A7aoteidtd7MGQc6dAYbWVvakFjy+eZY8IR
        GuhNkxb/uT8HZrPjVZZUPtw62poEnJpdhjOXnL1VdAY+cbA3cc2KBBsm9hwtZGQoC58I/7ARiBg2
        DYpT+2HIOgJGkw2ztqJTbIS7g5Sfv8e+77+iE7NKHYbvvvyM8311tVZ3M4WPL7w52tiGRUZTkVBZ
        UerWuCf//I0+3nHvfAeBYGParLupSDj66z4axeB6j7uQi055nQEfHC7Cdyol5gyZh/HR4xGUfxyG
        C8dgrMqH2eAZIxSLUMrqBIOTUCDo6iroJibrznIlKxbkEAqEveZc6rUQN1hW2BGDLE9GFclUaLyS
        AaE/Kxz7j3RymiWTOrGp16ftbacbKLsPVsz7PrAMkpgRHAdgQUPK16jf+xkspq6dZJtWAwT42JMW
        6zj8D5Ry+5RRWK7lkwuvA655kWCD9DMvgRfK/YcjePogRI6cAXnazzCxE4uhKJ0VC5UebzTVUaQS
        IWRiazIU8TM3MGbOLluE8lIN/rHiZQQEqfD8srXYtvl9l/uN6NufTtQk0bAg7yLCo+xVDGQSzzh9
        nD6PjnGvKUxtjTXMGh7Vj/P10PAo+kiSIwvzcx3G6wh5pXXYcLAO0X0CMS0qCUkDJ8E78zea4Ggs
        u0grXTrqkmcVCoxDWWRTiCOjsZNyI3g6D8FVsSDxUrAb+yhVQCRtXqHQNkgOgCHzdyoUhEERzUeE
        KCIO4qpimArPU1VB7vxdH6AQosBQiPtEN35eNnwq5IlzwZVazVw4gdqdK2DWdZ9ToI9cAq+r/Rpc
        OS3ayiMJZTV8p8frgR4jEmyY2DtRjUGKUp+hCL11MEISzkKZfoj9ch+GQZNF7xq7K2uBhOxIqE7t
        7wV/pZSajjSFCIQaLYPiigYUsCrcVl5EJvb333yBRgje2bANPr72zpekJnlMrLXfwiVNLcrZL2Zw
        SChum/MAfvhmG95a/DhefGM9BsYPo5GDLRtXIe/ieYT0Ccetd85z67htd2Taeu61eiJGbBAx4ymR
        YCO3uApbNALsZu9i7hs5FzPjE+GdkQLD5ROsWLjU4f2TREb2f1axwNMrIEnMjL6ebjZnWKFIDIlM
        4SAcBFzdTlvar64OhrOHIBt3OwTyZhU9QjGkgyfBEj2c/mg4vZ8VCtyTukDuA7/HVjYREgJaySDw
        do78WWorULN1GZj8ri93bIrK3y6yCsq5fy9bZQNxWWzgowjXBT1OJNggS2UFWhFKg0cgYHIcwoZO
        YcXCQTCXzkDfxdnrZI7tp/ahmb4SsetQPCkv8ldI6TYgzBfZBdXUY/ybnZ/QMsbb/ucBjJk4xeEz
        pBObrW6ZhPdsPP3quzRvYccn6/HMw7MglkhoXgGBLFc89dLbtCrBHUjEobK8FH+k/IyxN05zej3t
        z5TG53W1ni0Fs0GNW2p02HToMpIDFbhnxL0Y13cMggpOwqL1QPMYgQgWEREKRpdRBZ6ejdlkhF5b
        TTcbYhJdiHLve9C4n/J8MOePQZowhaMsUkabpdmew4VIIO3QSf5BqxgNqE3eAN2J/W06xs4gNMCe
        n8NlokSiDCTaQHAVafAUgyL8EMlRceEuxC46+UjHbeh5erBIsGEwWqCBF8oChiPwpjj0H3kR5jL3
        1uI9AWmZOjImCL7ezsKERAr0jJkGzL0kQofIglgkwOAof2jyL+Kzje/RPIInXnzT7XGz0k/i8IH/
        0AoHkpegDotAdWU5KspKkHnmBBUdt97hXiSBiBMiBH78dgcrUqZiwk0zGl8rLszD5nV2nwbG0Pkh
        xoKKeqw/cAl91f6Y3m82koLroT/BlXneVgTWqAI57VmhILA4Jzby9C6MBnYys7RtsiFRCuOVsxCH
        DYBQ1bf1D3QA5nIG6vds8mzSbjsJ9rOKHxKtrazjcFpsEmko7iQTJRvkukq29sJHOTxHjxcJNsiJ
        XWqWoVQ+GIgc3CVjkpN4fJzK4WQmuRO5mjpoKhucknpIZzVSjxylUrA3GgLodDos/N+HaNLSy29/
        AJmXe46ApLphycL7aY7AX/76Au6dv7CxwuH3Qz9hzfLnsO6txTSyMPvuh1rdX+L02TSCcOzwAby5
        +DGMZYVCVL9Y6pNAkilJnkTMwCF0XIWy5bppT3JZU43PyEZ/8uQikoBWP1hsu6R5IraNm7nThiE6
        zDkjva18/1sGMnPtInbM4AhMGR1Dn5dV1WPL96kdHqOzuHFYNG4Yxj1p1tTrsfnbzmrc5Yhd3HVe
        fZPQTw2hr6rT9m9DFBIJWcJNaDic3O1JsyFX8w0qavX0etqcYF+7SCBRP57rg14jEroasnRAIghN
        BUIxKwzSL1dSS1Eu6nVGZOVX02WDMQODsXTpUmRkZOC1117D5EkTOZupcLH943VUIMxIuoeKhKbc
        MPlWLH5zHc1V2LJpFW6ePbdV8UGSIP+29lN8uGYZfkzegT9/2083AokqPLt0NZY8ZY1KeCudzVN6
        PI2NoVyTOCoW44daEzhNZjOq69p3kTx2rgiZl+05HrF9+2DuzaPo85yCcmz5T1q79tvZiNhz5K0n
        Z0Mhl9Kfa7V67Nh7ArlFlfCWSVhxbKJLOl2Bpek4dGI1XxUOLQs9dyH9GKQJUwHOFuOWJq3MWxmr
        8ZiuQt1AHc8z0jfCd/4Kmo/A5J7t0HF3BHIDU6u1LldeKq7lfI83+57yq8mK5CbIXX4/V0KXTQnk
        GuiKn9MK3d5na3CJHJ72wYuEdtJXrXRYYiAT/5lc55phLkjSD3ElW79+Pf05OTkZu/fscfgCkQRB
        wq4vdyLl10MICQnB+5v/Rf/sfPop+jht1l2c+584ZSaUPr60aiE3J4taNbcGyWl45rWVeOiJF5F1
        9iTMJhP6DYxvrGwgvgwEdWikW79jb4ZMjA++vt0j+8rMLcF2drIllFe3kC3fzYSH+DYKBMLqrb9g
        3x+dlWhnsSYgu5z0XUwATbuAWlp5rwsEYimkQ6dA6BfC+bqpMBum4hz63FypoV0guSAJi/V7PmzS
        e+FqdcNN9zjlOYgj4+D/+CpUrJkPU7V7S6UFhRrsP+XZyM3u/7b8+v5f7c/NnWAXvc/je7w2kEjE
        7CaBj0IBP18l1CHB8JJxnzfXIrxIaAcktyAm1J6lTJYV0vPatmZeXW9o/KKRaIIrysrK6BYWZvdQ
        t1UbtBT69wsIptUSbU00JBbPTXMSCGSZgeQ++AcGI0jF4TXP027Ssgrodq0jlTheKjx/zBZrnggt
        Y+6eu0ASURPHjIYoLNbpjp9grtbAcOYgzHX2SJDIn1tMgNGj4ege6M/YZ1Zd6l6IQqIgjZ/YfGTI
        Rs2Acu6LqNm6HBam9fyE+oYGFGm6LveKx7MEBwWgX1QEBvSLgkh0zRkfO3BtH901Sniwd6NDGSG7
        oMbJmcwdvv3lNIqKi1HMbpfy8pFyPAs7/5tGt5lz7qfvWbDgMfr6yZMnGz8XGmFdF64pzMC4OBVu
        GKyiSx+kYoI0ZyHWzpoiq1ujKiTUYUwicIhrGtlIeSXhqy824ZGkcfhp5wa6r/gof/gp7Ep3b/JO
        +jh+0s30kYzRr4+Sjjl+EBk/BKMHBFGfd1ujGJ7ehbDZpFmn9WACq8VIe23QypNu9FEVqWMgjZtA
        Sx2dYCd95swhB4HQVowleajZ8jorNjgmd5EEytsXQj5xDqtP+Mtyb6esvBLH0s4g+Yf9yLmU192H
        0yL82dgO+jTpgkZ9G9rZU13uE4j8ahHOaSzIKmHvDiwKeidPNlsegdzbG2q1GiqVNYkqQCnFo49Y
        kxE3rl8LRlsFX28pQvy9aHQjcagaX3+ymiYtRsfEIar/wMbxqPlSbhYsNVdo97ZYVlQQsTN14iho
        iguxa+c29kqmow1fJrCTv4+3BOczTuEnViQQC+j7H30Kw/sHYhI7xsBwPzomKeckyy7BrOAgJaBj
        BwZToeGv6DnhtJ6Ij7cMowdH0M3fp/WEVzLJ9wsLxNj4SEwY2heDo0PgJW1/IJExuh9uJmP3DQ3A
        uCFRdOz4/mr4KGR0vd4uDroXoZ8K0qGTrWWNzTGbwGQfg6m04yV1+rMpqN21irh4Ob0mkCvh9/hq
        SGJHdXgcnp5Bg06H31NP4UDKH9Dru7/ChQt+uaGNkEnVz9s+AVbVGeBmc0pOymvdvyMjJUrqAH8M
        XfwC9uxOxvHjx5GQkIBnn30WI0eORFVVFT7//HPs27cPMpkXXvibo2vjL3uT8dHa5fS5raPmQPbu
        f0rCHPx99UikpaUhMTERzz33HF1a+HrPfvx7+2YYDHo8/vQrmDd7YmMCkg2SpEn21dQfgoiWsXHB
        SL/sibLF3s1dUxPw+Jzx9Pnloko8ufLfDq8Pjw3De4tm0eenzhdiyaYfkDQpHi/+ZTLkMmtODEmk
        PHg8B2u2HmTPR0fBqgpQYsEd4zBtzAD4KR0dCRmjCakZ+fh09x84m1PsdGz+Sjl2rHiQPhc1s+Le
        s25B43Ou4yaEqXzxyOwx7NixVlHQhJS0C3h9424YroEEM4HUi/ZmEPgGcb5u0uSCyTnuEUdX4upY
        v/djSAeNhzzxbif7Z1FIX/gtWImK1Q/BVNG+hmo8PY/C4hL88POvmJY4Hn6+zoZb3QkvEtqIUi5x
        WK7sylIg4uZIELF3Ox998Q2WvPwcDuz9jlZJNCU+Pp6KBYtvP1TVu1anpDIj0ltBU72++W4P7rl7
        LlKPHcWCBfYJgBgyLXzpLax957VGgUAu6/ml9f/P3nlAt1Wlefz/VC3J3Y7jxOmVJKSQThqQEBgS
        6oYMLLOEztAnS1nYIfTZWXbgTIAwB84GmMkQhg5hWAi9pJlUJ3ESO4mTOHGJe1GxZD1Jb993Hckq
        T7Yly3LJ/Z2jY0tX770r++m9737l/+FkldWXbElGQk6GkXkzKKRBq8dzh6VB04k+D2cDenk1n57c
        8n+tt4R6pOjv6h1PMiVgzqRh+P2tiwLc/3QDnzt5OJ5zBqZ+LZ07Do/etBA6rXLVgVajZiWN9Pjw
        +31Y/c6mANlwun95jx2M/+tK8/714sm4b/k8xWNvkQ2Ex9d8xowUxXnpjdAnpjH1RA2t7CnRrxPl
        gVpDeGNVkPetHTUd6mwqQw3NQ6DOkGLBZiYRHis8NjPM61ZBO2wCNEPGh4zrpyxE0nWPonHtI2H7
        RBiSMtBvWGyVTzldA4WPPB4X0+wQ7VY4bPWs0VwwtiY7vvlpGy69aC6Sk3pOFRk3EiIkWODDHkHH
        s7GqOohWUg8Mv3qSoIJL0GDldctw868WYcqYHLiKC33jJM5UWmODVtLgxcefQOkttyJv3x7U19cj
        OdGExfOmYeaUyVDJN44qmwWC2Hpxu3rRRVg0fQO7kXtqK0CfRNJoUWkRUXbahtWvrkO+vK/Cgnz5
        pHYjs182Zs9ZgEljBkEPUb5QimzmBacaUUUlUAK5kjVUgMbcz6QPQUpsFHIgg4IuuSZDfNUv+zJU
        avjEbYtD8gOIH3YehcPZ6rZfvmgy8zZ4cYpubMo7xjwGzfL7BmQmY9HM0cjpl+J7vzFBh+fe+DZg
        m43bWs69ZNlAmTt5mG/s69zDPoOiqj5QznvF0um459rW5DzydGzdV8yOfbq6AT/vLFA0EEhOOTE9
        BzqD0koq+vLKtmL8lKSoHT0zVFmRTVyUDYStrENkrHGVHpENhSeR9uCbEExBCcjy/9d06a3y9/4g
        bF+/pejBoM+kirOyLCd61PL5pdbooTemIDEjBw5rPay1pXAHiWhRyOHHLTtw2aL50Ol6xv+XGwkR
        og3KRI0kNpt1ZBOaNr0bVu/dH5+My2Z5pRY0lu73OzVtneV9Qk6NDV+gYUPLU/rnKrdsAvwb3tLl
        0Zu5MNb/TXTtP7GO/Vrj93LWmYc2ezSOL1yJ6pRWgR3yLFApqLffhE4Tn9r5swGK5RMkurTmgy3Y
        e7icufHnTxmO7Qdbk5/GDs3CA9fP8z0vKK7CY2u+QGVdYP372g3bcec1s3HjkmnsOXke8grLmOAT
        YbM78czalrq4MUP6BRgJz8rGhFuhDI5yHu5adr7v+fGyWhYioZAEQTkISkZyYvpAmNIGhLzelahT
        +0M3YQFpN4cOSh64TubLN/PCLkmlpH3ad3wB3RevI3HZQyHtqan3Q9K/PQXx1CE0H9zaBTPgdCcJ
        iWnQy8ahuaqYGQz+WKw27MjLx7xZPSM3hRsJEeJf1UA4IzASWAJUxWG4rTXtv7cXoEpIhFJCBgmu
        UJiDkhcNvageuKMMzkrF+mdviGib1z/OxZZ9nW9WRav7B17cwG6+BN34i0oCz6f7r5vHQglEWXUj
        7vvTJ+yGHwyt5v/y4VaWwLj84pamRXdfO4d5D5QMgI5wz/K5Pk8H6T7c8/wnvjyJcNULKVnDkJCk
        nA/QVQjyKlwzegYEbYK8fAvVp/BYapkXQXK30xRMPv+pWkEIEl7yWBsUkxMDNnU6YPlkNTTDJ0I3
        ZkboHLU6JP3Lv8NVIl8zzH3jmsFphbxBKf1HQKUpRVNDZcBY8akyDB86CDnZYUps4wg3EiLEFXTx
        1Kq7q+dkz4YU2chIUPCM93oozj5qcGZE2yQaY1Ma+v3Ooz4DQQmqIiCpZy9r3t+iaCD4Q3LKVyyY
        wIyFjBQjLpg6Aj/sKop4buTBoKoJLy+9u8kvkVJipY7BJGUMiruBwGYj3/yde76CM9wJKt/8Kcmw
        PTzyzbvyjgmhugq0fQfyGNz1lah9dln4bpXy9SaW+RCcngd9B9yiA822QE2bfQcK424kCArfB55V
        FiEuV+BKKLgddHciKDw6u300+yFIVZITe37Jb7sM7/yJraEfkk7enNe+94Lel1/Umkk/xy+sEAnT
        /IwT2idVXPhQ6LxJuQfG1O4T5yIjgBIDFR8dMBDYPsiT4LDBY7cGPuTXpA56Y8ijELK999Hc5KtE
        4vRdUrKGs1bn/tTVN6KiKr4eJEEVerXnnoQIaXIGXjxIWKgzkOWm7j8cauo2p2DFSc12iMX7/PrS
        K6MdNAamJb8Ned1dXwHbxjfgsbYtGa0ffz4M865VHJPsFti+ehOu6pI29+EPJVj2VShR77WPtkW0
        jf9NuDOcKG9bzGfS6FZlzvLqxpCyx3CUVjWyfAJi5KDIvCRezhvTemySm/ZPThQUku+SModEdRwO
        p69BVTamtIGw1AQKKx09fhLZWdF9H6NBdIYu7riRECGUmEfqiqozFleKqXMZqGwlYmuAbuJCCMkK
        JwOtRuQTSCzc2uaKguqrE5c9GPK66+RB2Dd90KaRoM4YiJS7VkM3dlbooOSB7fPX4A6KmXUUapfd
        16BVsjfrP95UN1jbHKdwgRdy/3/58u0RHyM7Pbo67WQ/g+R0jbl1QKEHg86QDI2uYwZMbBAUXakh
        SAh0nQU/b2ubjm5LoYj2Z8I5yzAkZ8BaVxZQzXK6oprJ96viVEpeVRO6COFGQoSQgdDYJDLlQ4Jk
        iL3Xh6j3aamDs2AL9FMvC1V8k08O7cipcMsWprs69vKdJCSTfP31ipuZAAAgAElEQVR/Qjd6uuK4
        8/AOWN5/vkN68v5ozuRqBIvwcLqWWOQ++DdyivbYTQ7/FUmooUjZ3fFCSDDCMPFiJIxbELdjhoWq
        JqpL4CzLh9tc0X5iJOesgRIZqUTS4Sf97RRFNJqtSEtNjsscKqtD8p2s3EiIAmoJ7TUSSA8gTTYU
        6iJQTlSCusuJqf2hHTM7NOygN7LOdM2/fMLilLGCVlaGWZfDuPgmxTpxT91pNK79D7hqSiPet+GM
        5G9fTFzsLVBogtz+3YG/loOgIISkM5jiNpf3y5KRqF8if4/idsjwSBLmjHBhQtVuGE/uRPOpvXBb
        KrmxwGFQWaQjqD9Ig9kcFyOhuqYeVltQWFtCLjcSoqCirgljc5J9IQfqgbD9cOc6spGLSSzaBXXa
        AKiyKPksqO+8/LpGNiDEAz91OKmqPTSDz0HyimdYTXbIfJrtzIPgLIgs9u7Fa0TxnKv4Yra2KoAe
        Plnl0zmIB/Vme4twBwLDHsF+NloxqbXt95uIFUdq6Abcc/Q68uq1GNlvES6aPAXzxh2CO/8nOE/L
        PxvLYyL9zOm9qLWhITiHI4bN1NogvyC09btKLXzEfcFRQNoIpbWtFleqfEMcktV5GU3JYYMz/0dI
        St4CeWWmHTYJ6uxRnT4OodIZkHT97xVlYQn75g9h27hWNkgiv2iR8dT/TBMs7kmIL/7qh6OiTECM
        lora1jwEKsUMh3CWh6Aot6ioyoG/Fifh8YaZ2DdvJTQL74Rh/KXQpA0OXw7J6fMICh7dJnvXS/+f
        LCln/SOCsEpNGm4kRMuxcnOAkNI5g1MwNAaGgqehEmLBFsClkAOg0UE3fh5UnYzn0oloXLwChrlX
        K46LRXmwvPtHeJqjq88mz4pOw0+t7mDnwdYKFNJyyErr2DlJTaaeuH0x7rh6NhbNGN3pY48YlOF3
        bO5OUoKSekstEl4+oMWfxAXMWPBcfB+Mk5bKxsIg2Vjoe0JknLZRKRgJLlfXdkmlEMP23ftD5yJI
        r+R++GBdt13Je/tlgwyEA8X1vs9BC2YyFKhvQcaZZMZooP25Th2UHwcUffVCUga0Y8+HoIm+qkI7
        YjKSblgFISH0BuIx18K87gm4ykJdT+1Bn5n6QlDLaC+RyFZzOk9ufnGAWuItV85sd5vsjCSsWDKd
        yTLfdtVMnDc2J6pj7zh0iilCEpSTcMOveoasbG+AQiKv7FfhJc8F2Db1XugvfxiGCZdAmzmSGwuc
        LoMkoL/7OZclSAYgoNztdvwP/dptfi1BKeW5l0HNjMhQOHdoms+tTtUO9CAjotHmZDdJGjOQnkIH
        77uUcyAW/gJVajZU6QMDB+WdUYhAspvhaahgJZLuNhILBWMS9FMXQ9vQ4koi48J02Z1QZyrcCMRm
        WD9bA8eebzss4EK5B6o0A4x6NQamG1mXTC8OpxuWdtT+OLGFpJC/3FqIK+a3hJGuufBc7D9aHrZk
        k+SbV9222NetkZo2UUfIaKCchC+2FrBjEtQJck9hKTbvLohqf2cb9I07ctqK41UafJV0Hq6ZPwlT
        GvZCV7AFzlN74WoohaTkYeT0HeKYxFVSVoHcXXvhVNBGgKS6a/s7T7P4IQ9+dZLy2iY0NbswaVi6
        bAi0uorI3d4vJTAJpW05pEA8shHgPPAT9DOvDF3xqzTMm0DlVKTW5tj8Xtj9qDMHI/WeV/xOPgGC
        Tg+lAm7H7m9g/fSliC5EQ/qZoB6RHvI69W7Yd7wO7t7uMuqF/OWDrUx5MTO1pYKAwggTRw3AXz/f
        iWq/nAVqGHX/r+cFeA4+/G6frxlTNJDIFDWColADeROev38plt5XjAZLJGf/2Q2FIUoaPFiTB4zI
        nIEr50zBmJG7YDyxA87iPbKh3xPKNDhdgdSJlugdpaauAQcKjqC0XFn7Rr5kv7T97Uc+9z7nRkIM
        aLA6sflgBXIyTBiYYWSJjLHI1/PUlEI8sgO6CfMp7TVwkMWu1BDUrrbFXgQyCtrPJHeVFMD896fg
        CdIPb4+i0mo0NhXDZm+G2yOxdsU15mbUyQ/W6c6ukJkbhy9CxwhnwYT+QQ8XV8ivtsybCQXF6DNU
        1DRix4HisPs1W5t84xabA6LTqShx7E+DxYo7/+s93Hz5TJgSWs6bFKMWK6+bg3qLnbWKNiXoWAfJ
        ugYLvt/e4mU4fLIa//h6j+Jno7il932ERH0YFFY9ZqsNd/7hPdx6xSxfm/DgzqmcjkF/3WM1zVhd
        A5yTswALpkzBrLGHoDmxl+mncPoeSm3NKXHxdGVL9Rx5eEXRBa1WE1YcjMZJXlmjVvueN8vXjfoG
        MyqqqmG2tNGFWJLWbx/leChgTtF+mM4y+8bnq+TD+zoiDxnYD7cuv6S7phNTqFMkud3JBU+rKfpf
        ivKSesz29Wj86LmIukCqkjORMHc5BGOK8hucdth/Xg/dqKnI/O/oy92avn8b9X++PSIvgmH0PPzZ
        cDl+qOQlDJyOQxr1/YZN7u5p9DroujIgRYerh7uRf6wGPzemdveUODHG43ahuji6cF9nESCtzh3p
        eBhPPx2wSuCehC6AVtSUj9AYZLCNiXA/VIWgHT0TgqHrhTQSZiyBYdZS2Ld+2uuTSjmcvghdV0rr
        m/EqiwZxA4ETM2ogSffmrn/sA6XBbjQSBH4vagNyO2lGnAfN4HHKYgOio2XV73S09HcIh1uEp7HG
        J8BENerknQiWf1YlZyD5pucglh2FWHwglh+Fw+FwOD0PBwS8IWi1T+W++WDYznHck9BDIdVF3bi5
        obkIBPUez/sGkrmaxaikJnPoe87grjqF+lfvhbu2pQuhoFYj8cp7YVx8c4gUs2boeKTe8QLqXlgB
        d0PnFCQ5HA6H0+Og1eIeedm5wSWK63e+t6rd1r7cSOiBqEwprFcDlBIOz8g3u8sKO9SvnqofXCWF
        cFWe9L1mXv8ctEPPhfac4K6PAiuXTFz2EMzrnuxQfkKCKQ2JafGT2OX0PppkY9YTIylxDqdPo5AM
        LL+0B4L0f9HuUiWgHB7YJUl1TK2X9m9961FLJNt3p5HAs90UELR6ZiCoUrIUx92VJyAe3dkhAyEc
        1E2ycd0TSH/k71ClZwcOqtRIXHoXXCfyYfvhnXb3pZeNBJMQWgLJ4XhxWOu5kcDhRIkK2JX79mNP
        dePxuw2ekxAES1QcORXqgaMV8xAk+WLrPLQZkti5hh8Uomje+z0sH7/IchZC5mFKQfKKZ6Ebo9w+
        msPhcDixR1EnQRD6x38mrfBi2x6Euv9waEfPYmJJIbhEiIXbIDXGpvUveSJsX70Fe+4/oWSvqQeM
        QModL0CdEt8mQRwOh3O2oqSTIEGKtDAupnAjoYdAFQfaCQsAXWirUBK3cZ3Mh6u0sMNyyR3BY61n
        AkquUmW9aP2581mPB5XeqDjO4XCAJEP0fVQ4nACUPMiSNHLC8qe7rYEHT1zsAbA8hAkXhM1D8NSW
        tXgRFEIDncV1qgDmv61C6u9ehyopI3BQpYbpsttlA+UgbBvfjItkKIfTk0k16TB3Qhamjc7E0P6J
        rJmbF6vDheOnzdh/oh4/7j2NWkv7YcEpI9Nx4aQB7HebQ8TajZE3VuP0bQRB0KXo9VfIv37cHcfn
        iYvdjFcwSZ09QnFcclhZHoLHYVUc7yx047fnfgbd2JlIXPZgSFmkoDch6TdPQjy+H82F27tkDhxO
        T4camf1m4UhcNHkAUz5UIjFBg0nD09njXy8cgY07S/GPH4+z3i7hGJRpko2EluThOtmo4EYCRwmP
        SnUzzkIjgScuyggJJgiGJLjLjyqOu6uK4alpt5QVnvpK2Dd/FLp9dYlsaLTdXEdyibB8+jITWFJn
        DFR4gwTduPPhLMrjXeg4Zx2zz+mH+68aD1NCxy+XZEhcPmswzhuVgaffzmMdYzmcqJFwyZwbX8ja
        9vYjsUlKiwAebuhmPE1mNO/+stP7cZ7Yj9o/LI96e3dtGRpe+12n58Hh9CUumZaDu5eODWimc+y0
        Bd/llbM28aU1TSxPiMaHZplYGOLK2YORYmoJIedkGPHHW6bhof/dAXNT7MOFnD5G+JwznUdwXyf/
        XBPH2TB44iKHw+EoMHlEOn67pNVAoBbOr/6zAA+v3clCCSXVNl8iMf0srrTi4y3FuOfVXOw62trE
        jVrGr7xmQrd8Bk4fwoOruuOw3WgkSDwngcPh9Ej0WjUeuGq8L/+ADIRn39nLPAjtVRjZHC48/34+
        jpa3yqVPHZXBHhxOW7SdHN49t0webogzqoQUVtLYE5CoSZSziSeHcDhBXDF7MDKSWysX1n1bxKoW
        OgoZFa9sOIRX7p7l80QsmzcMe4pqYz5XTt9BCEoc98Pq0QjPxHMuXngXyDjiGTgSCUtXdvlxnKIL
        bnegIaJSB518LhGaU/vgLtkHsaqoxWDg5gKHw7wHS2YM8j2vanDgy52lEe+HwhG7j9Zi+pgWQbLM
        FD2Mek2b1Q5e6H0zx2Zi1MBklt9A21Dy447DNThV1Xal08gBST7thqLTFljtIvqnGnDJtIHyHBJg
        aRLZvPYerwvrFRnWP5GFW3IyjcyrIro8qDU3M0OpsKSBta1uCwqxUD4GUVbb5EvcTDbqsGBifzZm
        TNCgWXTjSKkZ2w5VKf5dJg5LY/Pon2Zgx6yoa8LOIzUsLyQSBvczsf9Dtrwf+tvanS7UNDYj71gt
        isotMdWfiT3St3bBdcu+v60q646j9yBPQt+PPmxPmgyMnfj/7J0JeBRVtsdPVtIhgRCWkB0SQggE
        CWsIIAhRBwYFGRVxgYc6+imjM+76ZMaH+hwd1JlRn/s8R1EUjaCIiKhI2GSTLQthy8qWAFnIQlbS
        U/+bVPftSlV1Z+1Kcn/f11+6O9XVt6q76557lv9p9/f5csMOOpFzxua5vmHRkqFgFX1xkQyC346Y
        QJMiD5N/9i6qzv6V6gqzqb5GvxJCIOjqxIT5kT+nf4AQg71JUYtPfs6kLan5dDi3xCHdBHgdZk8I
        odumR7DJTMkdMyIpI6+E/vnVYSooqVTdx8LEIUx/ATyzYj/7+/SCUeTlaV0ooPJiS0o+/eOrdJvX
        DgvtTYuuHkLDpXOgxi3TBrMJ/7PNWfTzobOaxxE/rD/9fmaDUOC/fzhO3+4+ycpCb5gURu5utlHu
        a8cE0+JrhtBLX6SyZFCA0tDHboplxoqSBdJ+tqUV0JvrMqiq5rLmGEBUcC+66zdRFBOqfjw4z9n5
        ZdIY4SnS7JbsVFzMLtmHPnaOgQCcZiRIP7lq3iyorun6pXV1LA1D053UZlTWmalc8eMx1RK52lzn
        XCgpo5aSfYfTxIihdGVoPAWc3kvVmXuoriiXzNXlwq8g6JaMH2orRd6ayQPJjLg5AgyEB+fG0IxR
        gbrbwYh5+Z7x9NA7u5m2gh7wQtwzK9rGQJDJOHnR5jFCLHddG2VTyaEGvAR/vGE4jZBW+W9/e4SF
        VvTA7p6YP5Lio/trbuNj8qBld8TRw+/uIS8PN/rfxWOYB0OLK2MDyNXVhV5OStXcBudxyfXDmhgl
        SgYP9KVnF8bRexuOsYRUgS1OMxKkj61AmoRC5cel5WIF6wzOl9XSujKi7T1HUHzwEJobPYVM6clU
        hzDE+RNkrqkUYQhBtyJ8gHX1WlNXz9zRHQEEm2QD4cSZUjZh5Z6rYJNwhDSRzUkIs6yse3l70J3S
        hP7q6jTdfd4qrZSxLUD4o/RSDQVLq3QIP21Ly7dsh/e9+zfWFgFIvlyzI5d2HznPDBF4NWIH+dH8
        aYMpyL8hjJAY1zDWN9Ye1h3DnIlhFs/MLml/yYfOUkFJFdtn4uhAyzFjMr//umEU6N8Q4jh1oYLW
        7zlFx0+XMkNjRLgf3TRlEDMowOThAyhJOh9qRhgMPRgyMhcraizHA08IlDNjJSPnpisHsVAEDCNU
        spRK2+043OFSBFYMGPZwnifBxSVTOiGWNoOVVTVUWFJGff18nTWkbk1xRS1trHClLe6DaPaoJTR1
        5AnqdTSZak/sptoLCENUOHuIAkGHENTX2qukoLjS7kq5rfksOYu+2JpjEyfHRIjJC5oLyDkACTH9
        ydPdlRkyWmBCx/j/9kUqi+UDTIhDpH3AEAAwTu6TJmeZPMmYeH7lQRsBKOQLJKfk0/b0c/Tk/JEW
        bwsMhT1Hz7PJVwsYCDiWN9cdYaEbnvTcYnKVxiOrTsphDuQKvLgqxebYYCwczCyiV++dYKk6mTIi
        oImRACPiT5yBkJVfRs9+cpAZCjII/SAMhHPKH88f5sRQWm6JzbYdih0vjjNwWgmky2XzLuVzJ3K0
        Y1yC9geXJIQqvkytoOfywmlt1J1UdM2j5DNlEfUIHUNupt52XZECQWenh4f1stjRAkhIKPx8S7Zq
        Ih2S/D7dnGl5jJU3VsH2QGWGbCAA7Jsvz8RqGsYGwKT80ucpmgqRMDjg4j9TaPX8Lpg22O4YtqYV
        NDEQZNbuzLN5jDyDl5PSVI0fGASHsqzhH7WcBeR0yN4G7OuFzw5pTvo4nle+TGNJmQDejZnjgu0e
        T7thQE+C83QSPMyblE/tS1OXJhZ0PBfKauirjCpanh9JnwbdQrXXP06mCbdQj7Cx5OrVS7WlqUDQ
        FZDd8wCVAR3Jqi1Zuv9PyymxeSwrO+qhl2AIEmKsjeWSU87aGABqYPKGt0MGMX21yZrnG4UhwIMw
        CA88E3oVIPz4TCrJnYlxVmn5HyXDRDYAtIDxtX6PVfreXk5Ie2LEJnpOu9Lv/PCpVOmUHOCfO1dY
        QqlHc5w0IoEahZKxsDGrjh5ND6Bvou+kqpkPkXf8AvIMjWPNnwSCrkZZpXWCUkv4ay+wws/O109y
        xITGT6D2+kkgri+HFdQI9DfZVHLsSHcsHo/wAl/xgXwBLbBa10vexP95z0l6bonmtoD3Cnj3sP18
        cCwD/Lwsj/dxypd68O+JckuEYJyBjk6C03BqCaSZXN9xIfO7/HMbt+6nwSEDyaenl9bLBB0MC0PU
        1tOatApK7hlK04cupgmDEij4orSauCTCD4KuBSZiogZvgl6GfVuD0IYj+Q/QLKAedjdj5Bepl0nK
        BPp72zx2VH8A3gToNcCLAEL7a3sSistr7JaQ4t9ujZcSezoSejkYEYG2OW3QWLDn5QDKclMkd2Lc
        AicbCaaqS59WeZn+It21KJeUX6qkpA3baNG8RHKzU7oi6HiKKmppdTpKJyMp2COY8qqM5x4TCFrD
        WWliRZkfkP92BC3VYtDD3oQrx+5lmhNe4T0uvibtqaTSAfGotkI52c+bFN6i/fgqzkt3xqmzcHLS
        MvigmrQezD19jlau3UxV1cKSMyoIQ6QUuVJJnYH0uASCNgDiOjKQZnYk7q8HXy3R0djLg+Mn9+bm
        X/BeDw93Y7jJ+XyS1uDp4aSp0YCJi06/wu/6+Mk1Exf+baV093b++ayT+fT+qu/pusR4GhwS4KTR
        CQSC7gbEk+YmhFkeoyxvZ0bLaucRI3/rgQSmT3Aoq5g2HTjD5JCNAu8NUHoV7MGLFDWEaJwP7zlB
        ngNKH1tCrh3p63bDgNVjTjcSQJlv5X2+ZSbU0Uzin4duwkerf6LoiGAaGxtFkWGBIgQhEAjaFSSx
        YdKT8xGmjwpssZEwcViDyiB6FkAl8NdjjiXSdRQVVbbeAyTsORqLD+ASBEucpSuggE/SRLl2dkG5
        8zQPugiGMBLS31pWPn7x8hvdL5vXmYnGKf9/NOs0u3l6uFNQQF/q1dNEJq8eVF8v4uFqFFzQzw4W
        CATaoLZ+V8Z5mtYo8DN+aF+mR6As1bMHBH+un2j1SCDhbq/BjIQsRaIiEhGLHehUiaoKVAHI5Doo
        Pd3eKKsookN6saZY9sBnBa2ISju9INodEW7QZu+HT+RfdfOy6VUm0xdkpllq26C7Yc6pgo4emsCg
        QEYWevMAOvbKCwTikysen8ruo2Trxc9THN43LhjIjMYNGdMoFfPydCeTpxtbNRWXVbNVyqHMInbh
        d6Szn6DzkLQth3UrxGq0oafCcHr63/uapb44b3I4+97IQEzIaN8TeA3Q5VIuG0wcHeRQO+tpIwfa
        PD6cZ4yFCRQyISMtl3XOiAtyyEiYEhtAD88bQeVVdazTJBQqtQSl2pP6emN9P4ChfPdIZNwVUTmH
        6l3+KJlUpfZfIejOoMMbwApNbZXHl0MdUTSz0QLZ0ei098EjU2jpraNYtzzEpPv49GAGAoDuO1Zc
        EF15+Hcj2LYLEyM7tFzOqEBXYPE1UbZ15q6Gusw4BPQFfj5k7W0wVPquQb7XUd0EfDdunx5heQzj
        IGlrdpuPsy3glRAnxfRnx6oHvAg3T7WqLCLR054AU0fy437r8cRH92M9GvTA73bBtIbPCj0tUNng
        DAPBqBjv17tsWd2ulU+84WG+PMxM9Lr0jDH8WAJDgdXd4IEN9c9wdaqVjw0Jsl7ssvLt13/HRfjT
        60vimUxtc5K4MHHcOGUQvXZ/PGtx212Bjv6bDySwdsBdQb77/78/xlbZMtD3/+d98ayxkNw7QEm/
        Xl7M64DmQvw5eHf9UcPW3X+395SlsgFj/vNtcRb9AyX4XfxF+j9vBKIdtpFQHs8TN49kLbDVQPLl
        IzeOsPH4QBZbYMUw4QYl2z5ZCi3RP41Ysmypb6lprtmVZruYWWJjywpfBV2KkH7elpW7lpeA7yFv
        TyQGSWVoCsNnbLPY9JHzLNkMK8uSRlEYlMTh/SfGDKBJ0oQh694P7GOi5/9rDD363h67LXy7GnDv
        PnZTrLOH0aZg9b/0w32sqZKsl4DP+HFp0kG1Qkp2MRMrQhwb3qXIIF+KDundxID48MfjrJmQUcGE
        +vc16dLkP4pNqgjTvXLPeLYih0SytQtkH5ozMdTGgP5290nWb8JIIFFReTwvSp/h5pR82iP9nvOL
        K9nvHIuIOQmhlq6WAKFDbCewYlgjQQZJjdKflY03GnvvMm/3CvKvJ59AV7fL9qW0uiEu5PI8mc2T
        nT2O9oRf6fDNamy3afh6QBxHrwY8SrpYKA0EXCA/3Zwlrf6aTvZl0r5gNMCA+GRTJutZP2ZIX/Y/
        rLAemBNDz61sWemVwFjA7fzY+3vpUWm1ecVgf8vzqFaA50QPZNq/991RQxsIMshDWJ6Uxn4H8IzB
        0EGjI61mRygv/PqXPFqxyVheBBn5eB6aN5wtJmAsIASk15cBr0HrbbXmWt0ZwxsJSva9twzBL9xO
        OXssRiVh4fILXf1rHsWFErJVQgmYrOXkpRMaRgSAFwArYN5AeGf9Efr+19MOjeNCaRX9dVUK24dc
        7gaDISbMjzIMkswlaB1YmT6z4gALN8yOD6WR0opaK9wAYBzAyPzql9xOVX6HMk/8lu5IjGRNn7SO
        MTWnmD6TDGijJCtqgeNBKPK2GRG6xwNDcPX2HNq474wwEFTodEaCQACGhjQYCahnP3WhadJUOKfX
        rmck4KLPl3JhdeSogSCDjPe3vz0irTT7WGRhkfAojISuBVzRuCGxLTLQl0L692SubE93N6qsqWPe
        qqOnStlE66jEMoyJ7WkNFVuOqjI/+NZuctXpc/DKl6kWo1evz4EacMWjdTIS+GDoBvfzpt7enlQl
        /c4QWoFh4EhSH39cjpyLu/++3XLfXgUIfp9bGkMC9vZ9pugSOx78LtGECuqX+MzqLptZldLx06Us
        FCmMA22EkSAwNPAGqEmtyuEGlDyFD2iaLDg2qp/lPmLGcpMXXOBkwRVWxx4fatkOsddPN7fMfYoV
        4+ZDZ2n2hIb9jYvqyy7UypI5GCRylQQuyMh7QIw3MS6QlaEhuQ05EHpd8zBJoTQTF3Dch6F0obSa
        UrOLWRikueA8oBIE8XTE1n2l811TW88u1tgf2hOrhV2A/PkopYtDGydQUFfiRYXVxsl+by0IN0E1
        sS2UE/HZNVetEPkQepTrdH10FOyjwShq2eube1zNEWNqyTnDd9loGhWdBWEkCAzN7yaHs1W5FmED
        fFjGuR5LrhtmuY+Y47bGFQ4mWr5N7urtuc1eefHAXYnJ8mBmER04UahaU/+H62OYxwE8s2I/e79n
        bo+zaUyDEsxvduXRBxuP27y2rzTWhVcPYUmWWq7To6cu0kc/nnDIFYxJfP7UwTRDMlCUjXF4sFr7
        5fA5aTzHmmToQ76YlzCWeXbhaMv911bV0Krvdtodj0AgMB7CSBB0WxCnlIG7cVta6xLM0DoXrk1H
        8fX2pN/PHKo6QZ9WhFBQwvX0glF2G9jAG/DC4jH0wQ/Had2uk5rbhUkr/WcXjbHVM9AABgkME+hF
        PPLenk4VZxcIBK1DGAkCQwMXOuKHPGOjGmRyAeKTVQopVR+TO109Oojdh9seK3sZPn8hJsxaO517
        roJKLzWvC15ruW16hGWShju/vLKOhSPgJJC9HQDaC89JE7pcagnvA2K+WN0j3GLq4cbKPW+YHMbK
        uZDJDTXKMul4klXKuRAG+W/J4JDfG/v7Yd9ppkyHkAtcuX7S/2AUwIsjl/+hI+LtMyLorXVHLPva
        mprPYvA9vTzonllDLc+/v+GYpS/Ar+l5bXzmBAJBRyGMBIGh2X30PLvxxA5q0D9AnBGVCEpgRMhG
        wqaDZ1RX1JgoA7n6aLUKifYmuK83C0n83zcZtCW1gHkzUH6GyVlO3sIq/qlbRloMBLj7UV6pHC8U
        J5NTzrIafmThg/uvG8aaFSkTza4dE2QRj8F7Yn9pOcU22+A1SOqCEfbSXWMtOSAo+4MwkJwwhqQv
        3BC24Y0EZJbLWhGF+bb7FggEnQfjKS4KBDpg0kQeAlA2p5HhRZQw0anRu6eHTVyfV9brSFb8lMlW
        +3J2NbwivHY+BJt4FcflX6RqGjTwCLyclGqRyEV9ONQPlUznasW3SsaJ0kDggVfhs+Qsy2OERvg8
        DoFA0LURngRBpwJhBnlVraWiKPd0wMSbna9eJQD3OE95lWOhBiT52csLkDlxpkx3Asb4eN18NWZx
        YjYwHjJO6ickwlBYuzOPeRHAVVcE0r++P25T4vXzobMswfG73OoAABLQSURBVBGhjQ2/2pcbUZaY
        mnSSHAUCQddC/NoFnQq+aZOW/kFk4zbIM3C0VMrdwSZENySEWTwZ9sBkrWckYHx6NeEIiQwNseZN
        IAfBEfjSPDTjQYkoX1K5YW/zdMiaW27WFFGDLhB0VoSRIOhUxIZbO7phNawEWgOytrxej/sKhecA
        SXkdzdkife0A9IeQvSYAeQRXXTFQ5xUNuCqaK8H7oqe7wIP3G+BnYu89aKAv6wgIEZrW0fmbPQkE
        3RVhJAg6FXI/BqjbqeURRHMrbyTtaYFmTUgalJXp5Ax+exyRDJMinW5+sdKEyks864FqBj2UYQ10
        mmwJWh0tUQWB8Y4b2o+GBPnSQH9vpsUgEAgEMsJIEBgaiClNHWldPculj54ebqoiSvzEeuOUcPrt
        hBCb/6/46QSL7SM7Hwl+cuiAbyutB1/+p8ZHj13ZRH1QC3tufGXeREvhvREyyNuAyJRWS2AZuduh
        vWZGAoGgayKMBIGhQSb9oICmOQCY+NSe5+F7MsggRi+D2L1sJCDcAAMEpYRGAf0AeNBR0J6uvRrK
        BE8oPv75trgmxgPKHiHDnHeugglD4XUIU8DLIowEgaB7IowEgaFB3wVZ1x09D1DWB6AtryZ77Ne4
        isf/1DTsedllJALOmWgtEZw9IYTeWX+0TcffGiqrbT0NabklbPJuDTAMHpo3wmIg4Dyt2pJNmw+e
        pcIy9f4MoppBIOi+iF+/wNCs/DmT3cDD0uQ2rTFx7+F3djcRCUJi39sPTmL3Uf//+trDuvs+cvIi
        m3Rlb8I1Y4Jp/Z5ThvEmYFWP0kWXxkTE6JBerTYS0PiK1zmAkJOaKiOPoyWfAoGg6yHElASdBrn9
        M3oHqLWr5fMK0nIdU/lbscna9RHiSo70R9ACaomOJi06ArpVokxSZgYngqQH+jx8+efpzGB6btFo
        Sx4HGBpsPUfIiYDSoz2U1Q0avaVscHezbuQiSiAFAgcxXiWQMBK6IGYyt7aw3XDAPS5PdloCSbyR
        oKXGqARtmSEhLANvxIt3jbOb76AkLsKfXr13gk3OQ1uAHg0yMWF+THLaHgsTIxtlp02SUdDbpgqE
        Dx3I0sp6oL8DH5JR7kNrX16e1m1cXIXDUiBwBDWD2uxKZ50wFAvCSOiadLk2fQgJyDLKWiJKcvkj
        8g6aEzJ47evD0ordanigpwIm/AfnDrcIM6nha/JgugV/vXMsLVs4mr1OBmECLUXI5oDeE3x7ZoRc
        4CnQAk2jRnBaEmg5zVdR5BRYxwSJ5cnDB5AWCEssvXVUE8PHw63pakeZHwIBJxkXF9vLTP3lOun8
        tLwlt0DQVcFvQ4nZ7HJeZdMOQ5j4gk4B37FRTZoYcXtZQwFxe0dWyTLol7D0w/301PyRFDuoYYKF
        QZIYF8huSOiDYXLhYjWb/PtIkycy/mFAuKn43vOLK+mNtRmU7mDIw97Y/rEmjZ6VjBAcIzQPXlg8
        lnkYdqQXWPo0wIsya0II82jIwFBavT3XZn87M87T4muiWGgEPDAnhpVsoptjWWUt80AM7GOiqSMD
        aOa4EBZ6wTHjfMqhFLS4VoLQCCov5LbX2O8kyQCBwfbLAU/65qedNtvXVVeSh1fPJvsRCLoztdVN
        BdbMri45HT8SK8JIEHQKorhQglq4Aat4ufLhmEZTJz0gzvQ/Hx+gGyaF0/ypgyz7AhAY6hvd3+4+
        MKGv2ZFLX/+Sa1NF0VqgU7A8KY0emjecjQuGycxxweymBZIe0d1RqcWAfI4PNh6nJdc39HaAsYDu
        jbhhzMqySGwPT8vchDAa1WiAIK8BBooStJqWFSExzoSYRi/F5ZomRkJN5UVhJAgECqovNb121brV
        H3DCUCwII0HQKZBFf9B+uEilVI/v6aAm1+wIWC2v3p7DVumzxgezZk4Bfk21FpRAS2DzobPsdS3R
        MXAE5E3AM3BHYiRNHKZtsMBQwThWbs5k99X4Yf9pZjzcPTOKenFeAd5AgMHww77TlLQthxkK4QN8
        LEbClbEBTJRK6a351/fHyM/H08abAUICmso6V5YVU88+QfYPXCDoJtTX1lBNVZMQZeaBD57U7wLX
        zggjoSsCv7S562SU43COnyllMX6tXAPExOVSvow8/U6J9oDK4OdbstkNyZIIK6Bds6+3B1sh470K
        S6vZaj0j7yJdKHW8zfSb6zKY3kPD+zjWeVIG7/fS5ylMCyIu0p+NqVdPD7p82cxCBUjWhECUlnHA
        syU1nxkemPihvoiQQ7006WNMaK+N6hB+P9/tPUUHMq0trOHNUBoJ8MYs+/gAyx+JGOjDDIbisho6
        XXiJPLx8qLbK6gG6XFtFVeWF5OVjPxFTIOgOlJfkk/K67UK0zknD4ccg6GpMXLR8lfRlu4V/rn/4
        FeTqLurdBc6hqvQCXTxvmx/h6uZBfcOGk6uofhB0c2BAF51uIuQGt+QVuz5+MsMJQ7Igqhv+0969
        xcZRnXEA/86Z2ZvXJnUgtA40oQQCIlg0eO01DrSphFSpvFSqitTUbUwfKpW8VAjsEB5YqgIJBaFW
        vUiFtglOqEqqVqV9QK1apSLEDghVDUpLmkAgF+diE9/Xu96dc3rO7Mbx7vqS9V5mPPv/KSdjz65n
        jrOb2W/O5Tte5KFWBPCGYMO1ZJi5Ax6FlaLRCyfxfoWaJtLTNHLhw4L9TNJ+pwMEDUGCN+GqC+7C
        GDWsWlOwezo+pi6QJzElEmqSDhCGz51Q24KuxwkjKbc7Uad8CBIAoCoCdSvsFoV8yclhGj57jKzp
        qx/bAbDcJeMj9MmZ/1J6eqrwQSEfObh/+6nq16oQOgMBoGquWbWG0sl4wYVRzw8fOvMfqrtmFYVU
        Mf1Bh2oIUFl6/MHk8HkVJMwzC4vRnv5921+qbq3mhyABAKpGZ19sXL2ehgeOqUAhr+VASoqPXrSL
        6Q+RL1hHpi9ExDkxjFtwN/W6moE68qnXjdjyHQ+vP8B1oi/9O7Bifg/1/rzcZca4kfeQtDMp6hk9
        01PjZKUXSIgr2evjifh3l1L3SkGQAABVxQ1TBQq30cj5D3KmRc6mWxrmbIYFV2OXg4VgmHyBsB3o
        GWZg8R90gclLAzQx7OAyCZK93H9L/HsUi1Um2coSIUjwIBUAm7jxAjfTgcLK1evVRXmAJkcuYIaD
        R+i7aR34zQ7+9FRXHSzoXBl24BAIuW7RL11v+33oxLmJRrjg2/r2PfaqIxVYhLteKSgLdb3FgFRw
        P70WxcobKFC/kuLqDi4xUfpaF+A+eqprcnLULpfpMSeZgEGVUD2ZvqDD3RSOnDuhrtYvTZHxwyP7
        Hru4+NOdgSDBg9T/NYEbM1gudD/2ik/frAKGhB0o6A+T1HQcrQsepsej6DI1nsniqbspZrooAplW
        h2omf9PjDwLhFdUIVHVgcFCd8c+WMfXaO7tj5yt9wlIhSPAgdW11VZ8WwNUw1N1kuLHJLrr5Vw/0
        sgd86TnkYvFU00s1NnQ653sm5QmL2I8rdkKP4VyngbdMScbn1f1JRP0L3lHsMfTrrQf16TJzXBUk
        ZMY1XAke8gcFllOo4bqCIIERfWhJerGU46oAaIi4vGSSOPvW5xLH3DbmYDEIEgDAdewBcP66qpwr
        P0hQJz/7dm/PT6tycg9q3vJsYz03ouofslUy0a52taqy+DKqeXSCoWR6hJKT2bVY9GArFUjaQUMw
        EzSU8z3iDzXYY2V0YHqZJFojk+z37+zvdv0df6UgSAAAgLJ579XH9e34G9lii3Y9d6uRElGLs1ZG
        UgcQG9Vu/7wHmYtuIs3OepkaG7J36ZYFu3tiZnxD2B4ouSQqCAnq8TGjOcMDTCPIHlTbnyztoMsf
        ggQv8tgqkACwvB3e3X1cbXTZq7/f8PWYPxwKtxhSRCVjreqWXQUOcl2xx5XCKuim0GuEzO6iMNXX
        umXqagQbCoIERWwlBAkAAADVcXR/TGcU6ssW28aHnlkVtMyolLJdStbKmNTdFI3FHlsnK7Impq+M
        L1D3TL5sci4dOOigwU7SNQf7cX8wP9HX3fd0PXN73+4d7xdbFy9AkOBBUoW+BRN6+PLNggZQTZLJ
        uNN1qEX/+s2OQbX5S7bYNm3ducESspVJo10y0aY+8Zup2M8tKe2037oQZbopODfsYME3k/ip3h6P
        oOn1RSY+OZtzCGaZD6lNTwm/3rKFIMGDuJTjBZ0NQmA5L4A8c60+KYmPOFAVmMNbe7YfVRtdduvv
        N3fFggkKt0tpRZhlD4jsIMZuLPa4QndTxMfscpnhC9gtCYZR+LEoSG6hWOxxVWpuuVIECR4kGF1g
        eVGCZaWJm8WNEwLwOitVmEdf/d85PcdTwQUO7I7pfoAD2WJr6Xy6yc95uxRmVDKpB0a2qd31xR7b
        SiXtMo8b7zke+lIf0d+XUO1lDUGCBzESR/ObDVIqYtZNawBwxVxrR0gm3nOgKrBE7+59Qi+48Mds
        IXW3z+890dBssXRE3TBtYkJGiLENVGJbqjBkFyFIAC9ImvzNQCp3XyI+SnWNn3GmQgAulZgszLDH
        hex3oCpQLrGYOEj0b8qUX+ld0W/GrmFGuE2SFSHBopxRVBI1FXNYJunLlaiu22E0m0e1d+48oqLn
        5tn7rl1zx7yjegFqjW5aHjp9ND/986n+3p61TtUJqqdjy/NrhU72xGWrZNSqgoCI2r1Qc+sJ9d64
        tVr1cwu0JHgVo9fU3zlBwsTQWfpU0y0OVQjAXSYunZ1rfYj9TtQFqu/Qq49+rDa6/E5/r3M3NNbV
        N1uUbhcWtTGmgwZ2O2W6KRLE+RNO1tcpaEnwqI3f2bU6kKIP1JfB2ftXXH+TPcUHoJYlxi/R6MWT
        +bvTgvj6t3sfK3gAalPLN56/zvSlbye/dfzwy084s5a0wxAkeFj0W7teVC/w92fv08kYG1evt1dZ
        A6hF6eQkXRr4H0mRN5uNsV/0v9L9sDO1AnAnzJz3sND41FNqc2b2PiklDZ87fmXRFIAaoufFDw+c
        KAwQiM4HuW+HE3UCcDO0JHjcps7n7rOY/AfNMf6kbsX1VL/yBmIcsSJ4mw4KJocHaHJkzhZjwSR7
        oG9v9xtzPQhQyyq3ODe4wukjfzu1ZuP9Q1JdBPMfSyUn7dXUhEjbKUkNc4mrpwG4VDoxSfHRQRq7
        +FHOIkCzSUZP9vf2/LrKVQNYFtCSUCOiW3c+ygTbRQt0MdnLrvpD+gu7WwLcizNGhj9oL1pj+jOL
        0iw3+j0WHzmnPrx1QqOFLkXS/qMX6lngYJlt9jk63bKVSpCw0otUgp7q39sTK6LaADUFQUINae/c
        +aC6iOrkIhi16DHc8GUXq6nPLlgTUrGeu2c4jw2eoqmxQadOn2BMbOt75XG0IAAsAEFCjbn32y+s
        T8vUz9RLf7/TdYHK0q0LesGaTOBQl0mktdDdeJUNfnyERDq1+BPL758Gl9uyiwcBwALcc8WAqurY
        uvMBS9AjjNhmwiyXmsAYz7YyhO2gQW+dXPRreOBYtquhag6qd/qP+vf0vF7NkwIsZwgSalx714s3
        cTH9FUH0RSnlBqaXXZW0wul6QXVw00d+3dKgAgYzGzjoYKIadFeD7nKokHEpaUBt3zMYvSkN6699
        u3e8X6mTAXgVggTIFYvxlgEKmuO+BqerAvNjAR5iwrhTShGVkrcxJlvV7sbSD8zswau6xcHMtjhU
        ar0PKSwa/OiIPchwZh/RSJrJu8yUNe+avYtJN6TG311NCb3QT1kqClDDECQAeMSmrTs3WEIHCzyq
        Pm5VsRf4Knn0IucGmXY3RV22u6LenjJbDqMXPqTERMFKjF/r7+35Q1lOAAAlQZAA4FGbu2LBBIXb
        pbQiTLJWErKDdHdSGRi+QHZsQ6aY/jo75Xex7AyI547n7JPE/nS4t/ur5agnAJQGQQJADWnpfLrJ
        NHgHE0abJBFhxNqoDFNi9TgGMxDKCRwMM7D4D0qZmeWQm89gOpg2bjjw20eHSq0XAJQGQQJALYvF
        +L0nGpotlo5IRpvUbXyL2nsnlWHGy0zuhlBmYOR8uRvGh05TfPRi7s8y2nbolZ6fl1oHACgNggQA
        yLHh4Vh9w0S4XZIVIcGi6gM7KomaynFsUw+KnEn6VGd3U+j04JfO5E48kMT6Dvd2d5TjnACwdAgS
        AGBRrQ+98Fkjlf4CcbpbCoowRrqbouRc0JdzN0wnJq6kVs7inN1yaE/3B6WeAwCWDkECABRt8+aY
        mV5bf1daig712R5hJCLqcnJHOc/BSP6gr3f7k+U8JgAUB0ECAJRF85ZnG+u5ERWM2pg9BZN07oZV
        JRzyZH9vz81lqh4ALAGCBAComEjnrtt8KmAQRHeri42egnmX2n3VuaBTIWPVu7/ELAcApyBIAICq
        uakrFlwtwhuFlO2U6aLQLQ7r5nn6mf51U2uRORHAOQgSAMBR93U+3ZTkvhZO4h57UCTRnZJoUEUG
        D7+zd/shp+sHUMv+DzA8hVDWl3m/AAAAAElFTkSuQmCC
    </Bmp>
    <BkgAlpha>255</BkgAlpha>
    <Text></Text>
    <ImageRepresentation></ImageRepresentation>
    <AllowVerticalScrollBar>false</AllowVerticalScrollBar>
    <AllowHorizontalScrollBar>false</AllowHorizontalScrollBar>
    <ActionItems></ActionItems>
  </Layout>
  <PrintSettings></PrintSettings>
  <UserSized>true</UserSized>
</TextObjectProperties>
